Workbook

Sheet Sheet1
B2: ID | C2: NOMBRE | D2: DIRECCION PRINCIPAL | E2: ZONA | F2: CELULAR | G2: DNI | H2: FILTRO
B3: 1 | C3: ELITA TAMANI PACAYA (HENRY FLORES L.) | D3: CARR SUNAMPE NRO. PUERTA 391 B C.P. HUACA GRANDE - SUNAMPE | E3: ZONA: SUNAMPE – SAN IGNACIO | F3: 934500127 | G3: 76044922 | H3: =VLOOKUP(G3,consolidado!$A$2:$B$656,2,FALSE) -> #N/A
B4: 2 | C4: FACHO LOZADA AUGUSTO IGNACIO | D4: AV.PRINCIPAL 543 SUNAMPE LOTE 6A | E4: ZONA: SUNAMPE – SANTA ROSA | F4: 998530990 | G4: 43312934 | H4: =VLOOKUP(G4,consolidado!$A$2:$B$656,2,FALSE) -> #N/A
B5: 3 | C5: BARRUTIA NAPA GERMAN YSAIAS | D5: SUNAMPE PASO DE GOMEZ S/N | E5: ZONA: SUNAMPE – COLEGIO | F5: 979420182 | G5: 40339325 | H5: =VLOOKUP(G5,consolidado!$A$2:$B$656,2,FALSE) -> #N/A
B6: 4 | C6: PEÑA SOTO KATERINNE LIZETH | D6: Calle Nueva Esperanza Mz. A Lt. 12 -Grocio Prado | E6: ZONA: GROCIO - MEJILLONEROS | F6: 936691447 | G6: 47353719 | H6: =VLOOKUP(G6,consolidado!$A$2:$B$656,2,FALSE) -> #N/A
B7: 5 | C7: BEGAZO PEÑALOZA MILAGROS LUCIA | D7: Psj. San Cristobal 360 - Villa Julia | E7: ZONA: SUNAMPE – VILLA JULIA | F7: 925019236 | G7: 21869870 | H7: =VLOOKUP(G7,consolidado!$A$2:$B$656,2,FALSE) -> #N/A
B8: 6 | C8: RIQUELME APOLAYA VDA DE PEREZ GREGORIA ELISA | D8: Av. Melchorita Nº 604 - Grocio Prado | E8: ZONA: GROCIO - MEJILLONEROS | F8: 956698366 | G8: 21782120 | H8: =VLOOKUP(G8,consolidado!$A$2:$B$656,2,FALSE) -> #N/A
B9: 7 | C9: TASAYCO MAGALLANES ALICIA MARIA | D9: PSJ. DOS DE MAYO N°303 - CRUZ BLANCA | E9: ZONA: CRUZ BLANCA PARTE ALTA oruro | F9: 945857289 | G9: 41576648 | H9: =VLOOKUP(G9,consolidado!$A$2:$B$656,2,FALSE) -> #N/A
B10: 8 | C10: CAMPOS VILLA JOHN WILLIAMS | D10: Parada de los Amigos Pasaje Villa - Sunampe | E10: ZONA: SUNAMPE – SAN PILPA | F10: 967061773 | G10: 75347649 | H10: =VLOOKUP(G10,consolidado!$A$2:$B$656,2,FALSE) -> #N/A
B11: 9 | C11: LOYOLA SARAVIA ROBERTO CARLOS | D11: Parada de los Amigos Pasaje Renovacion - Sunampe | E11: ZONA: SUNAMPE – SAN PILPA | F11: 913789112 | G11: 47516353 | H11: =VLOOKUP(G11,consolidado!$A$2:$B$656,2,FALSE) -> #N/A
B12: 10 | C12: PONTE CERNA MARIBEL RUDI | D12: Pasaje Santa Rosa - Espalda de Cruz Blanca | E12: ZONA: CRUZ BLANCA PARTE BAJA | F12: 923757401 | G12: 32872532 | H12: =VLOOKUP(G12,consolidado!$A$2:$B$656,2,FALSE) -> #N/A
B13: 11 | C13: ABREGU NAPA FRANK ENRIQUE | D13: Pasaje Napa - Cruz Blanca | E13: ZONA: CRUZ BLANCA PARTE ALTA oruro | F13: 918104510 | G13: 77564718 | H13: =VLOOKUP(G13,consolidado!$A$2:$B$656,2,FALSE) -> #N/A
B14: 12 | C14: GARCIA CASTILLA MARITZA | D14: Prolongacion Alva Maurtua - Cruz Blanca (Ex toma de cala) | E14: ZONA: CRUZ BLANCA PARTE BAJA | F14: 917631665 | G14: 40231558 | H14: =VLOOKUP(G14,consolidado!$A$2:$B$656,2,FALSE) -> #N/A
B15: 13 | C15: GIRAO ATUNCAR JAVIER ORLANDO | D15: Av. Alfonso Ugarte Mz M Lt 5, CP San Pedro de Pilpa - Sunampe | E15: ZONA: SUNAMPE – SAN PILPA | F15: 987013897 | G15: 42567350 | H15: =VLOOKUP(G15,consolidado!$A$2:$B$656,2,FALSE) -> #N/A
B16: 14 | C16: CHAVEZ MARTINEZ MARTHA MARIA | D16: AV. PARAISO MZ C LT 27, LOMO LARGO - SUNAMPE | E16: ZONA: SUNAMPE – PARAISO | F16: 985 192 082 | G16: 45123518 | H16: =VLOOKUP(G16,consolidado!$A$2:$B$656,2,FALSE) -> #N/A
B17: 15 | C17: TORRES DEL AGUILA DORA ESTHER | D17: Psj 2 de mayo #285-4 cruz Blanca Referencia espalda del colegio 22234 | E17: ZONA: CRUZ BLANCA PARTE ALTA oruro | F17: 991427548 | G17: 41164414 | H17: =VLOOKUP(G17,consolidado!$A$2:$B$656,2,FALSE) -> #N/A
B18: 16 | C18: MAGALLANES ALMEYDA MARIA MIRTHA | D18: AV. ALVA MAURTUA N° 580 - CRUZ BLANCA - CHINCHA ALTA | E18: ZONA: CRUZ BLANCA PARTE ALTA oruro | F18: 922427114 | G18: 21878769 | H18: =VLOOKUP(G18,consolidado!$A$2:$B$656,2,FALSE) -> #N/A
B19: 17 | C19: GARCIA CARBAJAL MILAGRO MELCHORA | D19: barrio el tigre 280 av los proceres chincha | E19: ZONA: CRUZ BLANCA PARTE BAJA | F19: 966242063 | G19: 21862703 | H19: =VLOOKUP(G19,consolidado!$A$2:$B$656,2,FALSE) -> #N/A
B20: 18 | C20: DE LA CRUZ MANRIQUE NOLBERTO FLORECINDO | D20: calle San Vicente Ferrer 520 Sunampe | E20: ZONA: SUNAMPE – SAN PILPA | F20: 938429070 | G20: 21854378 | H20: =VLOOKUP(G20,consolidado!$A$2:$B$656,2,FALSE) -> #N/A
B21: 19 | C21: TORRES TASAYCO CARLOS EDUARDO | D21: PSJE SANTA ROSA Nro. Puerta 128 Cruz Blanca CHINCHA ALTA | E21: ZONA: CRUZ BLANCA PARTE ALTA oruro | F21: 972287862 | G21: 46928659 | H21: =VLOOKUP(G21,consolidado!$A$2:$B$656,2,FALSE) -> #N/A
B22: 20 | C22: ALMEYDA DE NAPA MARGARITA VICTORIA | D22: Av. paraíso - Lomo Largo - Sunampe ref: A 1 cuadra del hostal “El otro Sitio” | E22: ZONA: SUNAMPE – PARAISO | F22: 965189450 | G22: 21848813 | H22: =VLOOKUP(G22,consolidado!$A$2:$B$656,2,FALSE) -> #N/A
B23: 21 | C23: PACHAS DIAZ DAVID ERNESTO | D23: Psj. 2 de mayo - Cruz blanca | E23: ZONA: CRUZ BLANCA PARTE ALTA oruro | F23: 956 022 078 | G23: 46250661 | H23: =VLOOKUP(G23,consolidado!$A$2:$B$656,2,FALSE) -> #N/A
B24: 22 | C24: ESPINOZA MUÑOZ LILIANA LASTENIA | D24: Av. San marcelo 158 (Villa Julia) - Sunampe | E24: ZONA: SUNAMPE – VILLA JULIA | F24: 922393873 | G24: 21854605 | H24: =VLOOKUP(G24,consolidado!$A$2:$B$656,2,FALSE) -> #N/A
B25: 23 | C25: ALMEYDA GARCIA ABEL ARTURO | D25: Calle Grau 108 - Lomo Largo - Sunampe | E25: ZONA: SUNAMPE – PARAISO | F25: 914013935 | G25: 21854743 | H25: =VLOOKUP(G25,consolidado!$A$2:$B$656,2,FALSE) -> #N/A
B26: 24 | C26: MAGALLANES CRISOSTOMO KATHERIN CINTHIA | D26: PSJ DE LA CRUZ MATIAS - LOMO LARGO - SUNAMPE | E26: ZONA: SUNAMPE – PARAISO | F26: 902642312 | G26: 46175442 | H26: =VLOOKUP(G26,consolidado!$A$2:$B$656,2,FALSE) -> #N/A
B27: 25 | C27: GIRAO ATUNCAR LUIS CARLOS | D27: PASAJE SANTA ROSA 130 - 01 SUNAMPE | E27: ZONA: SUNAMPE – SAN PILPA | F27: 923311111 | G27: 47144583 | H27: =VLOOKUP(G27,consolidado!$A$2:$B$656,2,FALSE) -> #N/A
B28: 26 | C28: SARAVIA YATACO ARMANDO FELIX | D28: Psj. Betania interior 04 Nº 390 - Guayabo - Sunampe | E28: ZONA: SUNAMPE – VILLA JULIA | F28: 979645543 | G28: 41971143 | H28: =VLOOKUP(G28,consolidado!$A$2:$B$656,2,FALSE) -> #N/A
B29: 27 | C29: DIAZ MAGALLANES SANTOS MANUEL | D29: CRUZ BLANCA VIRGEN DEL CARMEN | E29: ZONA: CRUZ BLANCA PARTE BAJA | F29: 925064547 | G29: 21797192 | H29: =VLOOKUP(G29,consolidado!$A$2:$B$656,2,FALSE) -> #N/A
B30: 28 | C30: MESIAS GONZALES DIANA FIORELLA | D30: Calle los Próceres Lote 24-Cruz Blanca | E30: ZONA: CRUZ BLANCA PARTE BAJA | F30: 960544540 | G30: 45082671 | H30: =VLOOKUP(G30,consolidado!$A$2:$B$656,2,FALSE) -> #N/A
B31: 29 | C31: SARAVIA BENDEZU LUIS RICHARD | D31: Toma de cala Cruz blanca -. Virgen de carmen | E31: ZONA: CRUZ BLANCA PARTE BAJA | F31: 975537912 | G31: 21869687 | H31: =VLOOKUP(G31,consolidado!$A$2:$B$656,2,FALSE) -> #N/A
B32: 30 | C32: CONTRERAS ENRIQUEZ CARLOS JAVIER | D32: SANTA FE calle primavera lomo largo 441 | E32: ZONA: SUNAMPE – SANTA FE | F32: 956118797 | G32: 21877560 | H32: =VLOOKUP(G32,consolidado!$A$2:$B$656,2,FALSE) -> #N/A
B33: 31 | C33: TORRES ROMAN KATHERINE MILAGROS | D33: Av. Huascar 130 San IGNACIO | E33: ZONA: SUNAMPE – SAN IGNACIO | F33: 938358973 | G33: 46294714 | H33: =VLOOKUP(G33,consolidado!$A$2:$B$656,2,FALSE) -> #N/A
B34: 32 | C34: TASAYCO GARCIA DANIEL | D34: Av San Francisco 117 sunampe | E34: ZONA: SUNAMPE – SAN IGNACIO | F34: 922771211 | G34: 21845817 | H34: =VLOOKUP(G34,consolidado!$A$2:$B$656,2,FALSE) -> #N/A
B35: 33 | C35: ABURTO DE LA CRUZ CARMEN ROSA | D35: SAN IGANCIO PASANDO Cevicheria de san ignacio | E35: ZONA: SUNAMPE – SAN IGNACIO | F35: 936972485 | G35: 41615897 | H35: =VLOOKUP(G35,consolidado!$A$2:$B$656,2,FALSE) -> #N/A
... B41: 39 | C41: LAZARO CANCHARI NESTOR BALVIS | D41: C.P. CONDORILLO ALTO MZ L LT 10 - CHINCHA | E41: ZONA: CONDORILLO PARTE ALTA | F41: 910925866 | G41: 21856980 | H41: =VLOOKUP(G41,consolidado!$A$2:$B$656,2,FALSE) -> #N/A
B42: 40 | C42: CARBAJAL NAVARRO CRISTHIAN JUNIOR | D42: Av. Alva Maurtua S/N - Cruz Blanca | E42: ZONA: CRUZ BLANCA PARTE ALTA oruro | F42: 924 343 517 | G42: 76564222 | H42: =VLOOKUP(G42,consolidado!$A$2:$B$656,2,FALSE) -> #N/A
B43: 41 | C43: SOTELO MATTA GUISELLA ESPERANZA | D43: PSJ. ANDRES AVELINO CACERES 137, SANTA ROSA - SUNAMPE | E43: ZONA: SUNAMPE – SANTA ROSA | F43: 929 564 075 | G43: 70401928 | H43: =VLOOKUP(G43,consolidado!$A$2:$B$656,2,FALSE) -> #N/A
B44: 42 | C44: CHAVEZ YATACO JESUS ALBERTO | D44: Psj. Santa Rosa S/N - Cruz Blanca | E44: ZONA: CRUZ BLANCA CAMPO | F44: 921159983 | G44: 43350897 | H44: =VLOOKUP(G44,consolidado!$A$2:$B$656,2,FALSE) -> #N/A
B45: 43 | C45: PAEZ SOTELO HELLEN VICTORIA | D45: Calle San Antonio 301 - Sunampe | E45: ZONA: SUNAMPE – SAN IGNACIO | F45: 991881274 | G45: 43073315 | H45: =VLOOKUP(G45,consolidado!$A$2:$B$656,2,FALSE) -> #N/A
B46: 44 | C46: GARCIA GARIBAY EMILIA MELCHORITA | D46: C.P. CONDORILLO ALTO, CRUZ DEL ROSARIO MZ A LT 12 - CHINCHA | E46: ZONA: CONDORILLO PARTE ALTA | F46: 977207233 | G46: 43081077 | H46: =VLOOKUP(G46,consolidado!$A$2:$B$656,2,FALSE) -> #N/A
B47: 45 | C47: MAGALLANES APOLAYA ENRIQUE JAVIER | D47: AA.HH. LA UNION HACE LA FUERZA MZ. D LT. 05, MINA DE ORO - SUNAMPE | E47: ZONA: SUNAMPE - MINA DE ORO | F47: 923385901 | G47: 21879863 | H47: =VLOOKUP(G47,consolidado!$A$2:$B$656,2,FALSE) -> #N/A
B48: 46 | C48: LEVANO VERGARA PIERO ALEXANDER | D48: A.v Alva Maurtua Nº106- Cruz Blanca | E48: ZONA: CRUZ BLANCA PARTE BAJA | F48: 927 288 221 | G48: 76699951 | H48: =VLOOKUP(G48,consolidado!$A$2:$B$656,2,FALSE) -> #N/A
B49: 47 | C49: GONZALES NAPA WALTER MARTIN | D49: AV. ALVA MAURTUA N°508 - CRUZ BLANCA | E49: ZONA: CRUZ BLANCA PARTE ALTA oruro | F49: 980105151 | G49: 42697575 | H49: =VLOOKUP(G49,consolidado!$A$2:$B$656,2,FALSE) -> #N/A
B50: 48 | C50: DE LA CRUZ OLIVARES ROSA ALBINA | D50: Av. Alva Maurtua Nº 300 - Cruz Blanca | E50: ZONA: CRUZ BLANCA PARTE ALTA oruro | F50: 984786637 | G50: 21811546 | H50: =VLOOKUP(G50,consolidado!$A$2:$B$656,2,FALSE) -> #N/A
B51: 49 | C51: MARTINEZ QUIROGA ROMAIN VICTOR HUGO | D51: Av. Primavera 130 - Lomo Largo -Sunampe | E51: ZONA: SUNAMPE – PARAISO | F51: 917631684 | G51: 41413801 | H51: =VLOOKUP(G51,consolidado!$A$2:$B$656,2,FALSE) -> #N/A
B52: 50 | C52: SEBASTIAN SARAVIA JUNIOR RAFAEL | D52: Av. Alva Maurtua 514 - Cruz Blanca | E52: ZONA: CRUZ BLANCA PARTE ALTA oruro | F52: 968246931 | G52: 70366439 | H52: =VLOOKUP(G52,consolidado!$A$2:$B$656,2,FALSE) -> #N/A
B53: 51 | C53: BELLEZA CARPIO VDA DE AROSTEGUI MARIBEL VIOLETA | D53: AV.PARAISO CASA DE 2 PISOS AZUL - Sunampe | E53: ZONA: SUNAMPE – PARAISO | F53: 965808498 | G53: 21866027 | H53: =VLOOKUP(G53,consolidado!$A$2:$B$656,2,FALSE) -> #N/A
B54: 52 | C54: HERRERA CASAS DE CHINCHAY MARIA ANTONIETA | D54: Calle el Carmen Nº 163 - Cruz Blanca | E54: ZONA: CRUZ BLANCA PARTE BAJA | F54: 992870887 | G54: 21860894 | H54: =VLOOKUP(G54,consolidado!$A$2:$B$656,2,FALSE) -> #N/A
B55: 53 | C55: CARBAJAL CASIANO NATHALY ROSSIEL | D55: Psj. 2 de Mayo 285- Cruz Blanca | E55: ZONA: CRUZ BLANCA PARTE BAJA | F55: 916486489 | G55: 46927424 | H55: =VLOOKUP(G55,consolidado!$A$2:$B$656,2,FALSE) -> #N/A
B56: 54 | C56: MESIAS TORRES MIRIAM MARLENI | D56: Psj. Napa S/N - Cruz Blanca | E56: ZONA: CRUZ BLANCA VIRGEN CARMEN | F56: 923160732 | G56: 70365697 | H56: =VLOOKUP(G56,consolidado!$A$2:$B$656,2,FALSE) -> #N/A
B57: 55 | C57: CRISOSTOMO CUELLA LUIS ALFONSO | D57: A.v Los Proceres s/n -SUNAMPE | E57: ZONA: SUNAMPE – COLEGIO | F57: 949645226 | G57: 21846794 | H57: =VLOOKUP(G57,consolidado!$A$2:$B$656,2,FALSE) -> #N/A
B58: 56 | C58: CHAVEZ ALMEYDA CAROLINA | D58: PSJ. EL CARMEN MZ D LT 11 ( AL COST. DEL COLEGIO) | E58: ZONA: SUNAMPE – COLEGIO | F58: 953309019 | G58: 21866012 | H58: =VLOOKUP(G58,consolidado!$A$2:$B$656,2,FALSE) -> #N/A
B59: 57 | C59: BONIFACIO QUISPE EVER PABLO | D59: AV. La alameda s/n Sunampe | E59: ZONA: SUNAMPE – SANTA ROSA | F59: 936357730 | G59: 72801045 | H59: =VLOOKUP(G59,consolidado!$A$2:$B$656,2,FALSE) -> #N/A
B60: 58 | C60: DE LA CRUZ QUISPE LILIANA | D60: Calle las Nazarenas, S/n Huaca Grande- Sunampe | E60: ZONA: SUNAMPE – HUACA GRANDE | F60: 977265651 | G60: 06799544 | H60: =VLOOKUP(G60,consolidado!$A$2:$B$656,2,FALSE) -> #N/A
B61: 59 | C61: MENDOZA VELASQUEZ MARICRUZ | D61: LOS ARENALES, PSJ SANTA ANGELA - CRUZ BLANCA | E61: ZONA: CRUZ BLANCA VIRGEN CARMEN | F61: 998223499 | G61: 45271647 | H61: =VLOOKUP(G61,consolidado!$A$2:$B$656,2,FALSE) -> #N/A
B62: 60 | C62: VENEGAS CHAUPIN PABLO | D62: PSJE ALMEYDA Nro. Lote 134 27 Sin Barrio C.P. San Ignacio , SUNAMPE | E62: ZONA: SUNAMPE – SAN IGNACIO | F62: 998862290 | G62: 28296257 | H62: =VLOOKUP(G62,consolidado!$A$2:$B$656,2,FALSE) -> #N/A
B63: 61 | C63: QUISPE PAUCAR SANTA LUCIA EUGENIA | D63: CC.PP. NUEVO CONDORILLO - SAN VALENTIN A-1 | E63: ZONA: CRUZ BLANCA CAMPO | F63: 955176660 | G63: 44051352 | H63: =VLOOKUP(G63,consolidado!$A$2:$B$656,2,FALSE) -> #N/A
B64: 62 | C64: SARAVIA MEDINA LUIS | D64: AV. LOS ANGELES Nª 512 - LOMO LARGO - SUNAMPE | E64: ZONA: SUNAMPE – PARAISO | F64: 977537270 | G64: 71616237 | H64: =VLOOKUP(G64,consolidado!$A$2:$B$656,2,FALSE) -> #N/A
B65: 63 | C65: MARTINEZ CASTILLA ANA CECILIA | D65: PSJ JOSE SANTOS CHOCANO 145 - San Pedro de Pilpa | E65: ZONA: SUNAMPE – SAN PILPA | F65: 934981060 | G65: 43413495 | H65: =VLOOKUP(G65,consolidado!$A$2:$B$656,2,FALSE) -> #N/A
B66: 64 | C66: FUENTES CHAVEZ LUIS ARMANDO | D66: Calle los Angeles 449 - Lomo Largo | E66: ZONA: SUNAMPE – PARAISO | F66: 937002689 | G66: 44077389 | H66: =VLOOKUP(G66,consolidado!$A$2:$B$656,2,FALSE) -> #N/A
B67: 65 | C67: PACHAS LEVANO PATRICIA DEL PILAR | D67: HUACA GRANDE - SUNAMPE | E67: ZONA: SUNAMPE – HUACA GRANDE | F67: 964901936 | G67: 40956555 | H67: =VLOOKUP(G67,consolidado!$A$2:$B$656,2,FALSE) -> #N/A
B68: 66 | C68: SARAVIA PACHAS LIDIA | D68: Av. san antonio, guayabo psj. 29 | E68: ZONA: SUNAMPE – SAN IGNACIO | F68: 944804574 | G68: 21880000 | H68: =VLOOKUP(G68,consolidado!$A$2:$B$656,2,FALSE) -> #N/A
B69: 67 | C69: PADILLA ACEVEDO ARALI NERIDA | D69: Calle santa angela, frente al mega mercado - Cruz Blanca | E69: ZONA: CRUZ BLANCA VIRGEN CARMEN | F69: 997216682 | G69: 48477799 | H69: =VLOOKUP(G69,consolidado!$A$2:$B$656,2,FALSE) -> #N/A
B70: 68 | C70: NAVARRETE QUISPE NELSON NOEL | D70: Calle Santa Rosa - Sunampe | E70: ZONA: SUNAMPE – SANTA ROSA | F70: 986 252 415 | G70: 44071823 | H70: =VLOOKUP(G70,consolidado!$A$2:$B$656,2,FALSE) -> #N/A
B71: 69 | C71: GONZALES PEÑA ANA YSABEL | D71: AV.SANTA ROSA 146 SUNAMPE | E71: ZONA: SUNAMPE – SANTA ROSA | F71: 933 227 205 | G71: 21852326 | H71: =VLOOKUP(G71,consolidado!$A$2:$B$656,2,FALSE) -> #N/A
B72: 70 | C72: SOTA PACHECO HARRY ANGEL | D72: AV. ALVA MAURTUA MZ. B LT. 17 - CRUZ BLANCA | E72: ZONA: CRUZ BLANCA PARTE BAJA | F72: 934439107 | G72: 41951909 | H72: =VLOOKUP(G72,consolidado!$A$2:$B$656,2,FALSE) -> #N/A
B73: 71 | C73: CASTAÑEDA SULCA BRIGIDA DIONICIA | D73: Cruz Blanca Psj estrada 2 de mayo | E73: ZONA: CRUZ BLANCA PARTE ALTA oruro | F73: 991902168 | G73: 77100370 | H73: =VLOOKUP(G73,consolidado!$A$2:$B$656,2,FALSE) -> #N/A
B74: 72 | C74: UCEDA GONZALES VDA DE PALOMINO TERESA SILVANA | D74: Villa Julia - Sunampe | E74: ZONA: SUNAMPE – VILLA JULIA | F74: 918709040 | G74: 21879925 | H74: =VLOOKUP(G74,consolidado!$A$2:$B$656,2,FALSE) -> #N/A
B75: 73 | C75: JUAN EDUARDO MALASQUEZ CHICO | D75: ENTRADA SANTA FE, CAMINO EL SOCORRO - SUNAMPE | E75: ZONA: SUNAMPE – SANTA FE | F75: 952631213 | G75: 21887388 | H75: =VLOOKUP(G75,consolidado!$A$2:$B$656,2,FALSE) -> #N/A
B76: 74 | C76: CURACA CUSIPUMA MANUEL ENRIQUE | D76: Virgen del carmen mz lote 11 Cruz Blanca | E76: ZONA: CRUZ BLANCA VIRGEN CARMEN | F76: 923 144 872 | G76: 71717330 | H76: =VLOOKUP(G76,consolidado!$A$2:$B$656,2,FALSE) -> #N/A
B77: 75 | C77: CHUMBIAUCA ALMEYDA MARCELO | D77: Av. Principal Cacerio Huaca Grande | E77: ZONA: SUNAMPE – COLEGIO | F77: 933 396 143 | G77: 41764623 | H77: =VLOOKUP(G77,consolidado!$A$2:$B$656,2,FALSE) -> #N/A
B78: 76 | C78: CHUMBIAUCA LEVANO LUIS | D78: Paso de gomez , empezando huaca grande sunampe | E78: ZONA: SUNAMPE – COLEGIO | F78: 971054315 | G78: 44338673 | H78: =VLOOKUP(G78,consolidado!$A$2:$B$656,2,FALSE) -> #N/A
B79: 77 | C79: DE LA CRUZ HERNANDEZ RICHARD LEONARDO | D79: Prolg. Paraiso S/N Lomo Largo | E79: ZONA: SUNAMPE – PARAISO | F79: 951 138 073 | G79: 21882415 | H79: =VLOOKUP(G79,consolidado!$A$2:$B$656,2,FALSE) -> #N/A
B80: 78 | C80: ALFONSO TORRES NOEMI MARLENY | D80: CL. SAN JUAN S/N - SAN PEDRO DE PILPA - SUNAMPE | E80: ZONA: SUNAMPE – SAN PILPA | F80: 943475536 | G80: 43271704 | H80: =VLOOKUP(G80,consolidado!$A$2:$B$656,2,FALSE) -> #N/A
B81: 79 | C81: TORRES SANCHEZ HUGO ALBERTO | D81: CALLE SANTA ROSA #355 PRIMERA ENTRADA - SUNAMPE | E81: ZONA: SUNAMPE – SAN IGNACIO | F81: 944323513 | G81: 46865852 | H81: =VLOOKUP(G81,consolidado!$A$2:$B$656,2,FALSE) -> #N/A
B82: 80 | C82: NAPA ROJAS HUGO EDUARDO | D82: Av San Pedro de Pilpa 475 | E82: ZONA: SUNAMPE – SAN PILPA | F82: 933 410 312 | G82: 42652351 | H82: =VLOOKUP(G82,consolidado!$A$2:$B$656,2,FALSE) -> #N/A
B83: 81 | C83: QUISPE VASQUEZ JOSE ALEXANDER | D83: VILLA JULIA PSJ LOS LAURELES | E83: ZONA: SUNAMPE – VILLA JULIA | F83: 939 584 261 | G83: 75449009 | H83: =VLOOKUP(G83,consolidado!$A$2:$B$656,2,FALSE) -> #N/A
B84: 82 | C84: AGUILAR RIVERA NATALY CRISS | D84: CL. ALFONSO UGARTE N° 160, SAN PEDRO DE PILPA - SUNAMPE | E84: ZONA: SUNAMPE – SAN PILPA | F84: 957408746 | G84: 44658446 | H84: =VLOOKUP(G84,consolidado!$A$2:$B$656,2,FALSE) -> #N/A
B85: 83 | C85: CHACALIAZA ATUNCAR HEBER TOMAS | D85: CL SAN VICENTE FERRER NRO. LOTE 01 PSJ. 8 C.P. SAN PEDRO DE PILPA - SUNAMPE | E85: ZONA: SUNAMPE – SAN PILPA | F85: 955974625 | G85: 45470570 | H85: =VLOOKUP(G85,consolidado!$A$2:$B$656,2,FALSE) -> #N/A
B86: 84 | C86: YATACO VIDAL JAIME JUAN | D86: Calle Parada de los amigos 409 - Sunampe | E86: ZONA: SUNAMPE – SAN PILPA | F86: 989058641 | G86: 06093318 | H86: =VLOOKUP(G86,consolidado!$A$2:$B$656,2,FALSE) -> #N/A
B87: 85 | C87: VILLA CASTILLA NANCY | D87: Calle San Vicente ferrer 300 - Int. 10 - Sunampe | E87: ZONA: SUNAMPE – SAN PILPA | F87: 947151746 | G87: 70401918 | H87: =VLOOKUP(G87,consolidado!$A$2:$B$656,2,FALSE) -> #N/A
B88: 86 | C88: GALINDO SALAS LIZET | D88: Calle Parada de los amigos - Psj Villa - Sunampe | E88: ZONA: SUNAMPE – SAN PILPA | F88: 972841510 | G88: 45851431 | H88: =VLOOKUP(G88,consolidado!$A$2:$B$656,2,FALSE) -> #N/A
B89: 87 | C89: CARBAJAL SANCHEZ DE MARTINEZ ROSA ERLINDA | D89: Calle Parada de los amigos - Sunampe | E89: ZONA: SUNAMPE – SAN PILPA | F89: 952 567 956 | G89: 45715311 | H89: =VLOOKUP(G89,consolidado!$A$2:$B$656,2,FALSE) -> #N/A
B90: 88 | C90: MARTINEZ MARTINEZ SONIA | D90: cruz blanca - psj napa | E90: ZONA: CRUZ BLANCA PARTE ALTA oruro | F90: 977873933 | G90: 41731879 | H90: =VLOOKUP(G90,consolidado!$A$2:$B$656,2,FALSE) -> #N/A
B91: 89 | C91: DE LA CRUZ ABREGU GIAN CARLOS | D91: AV ALVA MAUTUA PUERTA 627-B - CRUZ BLANCA | E91: ZONA: CRUZ BLANCA PARTE ALTA oruro | F91: 924144569 | G91: 46869547 | H91: =VLOOKUP(G91,consolidado!$A$2:$B$656,2,FALSE) -> #N/A
B92: 90 | C92: VELASQUEZ DE LA CRUZ LUISA HERMELINDA | D92: Pasaje Jose Olaya- Entrada Condoriilo | E92: ZONA: CRUZ BLANCA PARTE ALTA oruro | F92: 969738812 | G92: 43221317 | H92: =VLOOKUP(G92,consolidado!$A$2:$B$656,2,FALSE) -> #N/A
B93: 91 | C93: VASQUEZ MARTINEZ LUIS ALBERTO | D93: CRUZ BLANCA PSJ TUPAC AMARU ENTRADA CONDORILLO | E93: ZONA: CRUZ BLANCA PARTE ALTA oruro | F93: 947821195 | G93: 21869218 | H93: =VLOOKUP(G93,consolidado!$A$2:$B$656,2,FALSE) -> #N/A
B94: 92 | C94: SOTO NAPA OSWALDO GUSTAVO | D94: Av. San Cristobal 155- San Ignacio-Sunampe | E94: ZONA: SUNAMPE – VILLA JULIA | F94: 921574409 | G94: 46952075 | H94: =VLOOKUP(G94,consolidado!$A$2:$B$656,2,FALSE) -> #N/A
B95: 93 | C95: GARCIA BAUTISTA MIRIAM LIZET | D95: CRUZ BLANCA PSJ SAN MARTIN 55 | E95: ZONA: CRUZ BLANCA PARTE BAJA | F95: 975342591 | G95: 45200955 | H95: =VLOOKUP(G95,consolidado!$A$2:$B$656,2,FALSE) -> #N/A
B96: 94 | C96: PEREZ ROMERO NELBIS MARIA | D96: PSJ. SAN MARTIN - SAN IGNACIO - SUNAMPE | E96: ZONA: SUNAMPE – SAN IGNACIO | F96: 934453865 | G96: 44483361 | H96: =VLOOKUP(G96,consolidado!$A$2:$B$656,2,FALSE) -> #N/A
B97: 95 | C97: BONIFACIO BALLARTA SANDRA GIANELLA | D97: AA.HH. VIRGEN DEL CARMEN MZ C - LT 07 - CRUZ BLANCA - CHINCHA | E97: ZONA: CRUZ BLANCA VIRGEN CARMEN | F97: 961576371 | G97: 73479221 | H97: =VLOOKUP(G97,consolidado!$A$2:$B$656,2,FALSE) -> #N/A
B98: 96 | C98: GARCIA DE GARCIA GLADYS | D98: CRUZ BLANCA VIRGEN DEL CARMEN AV TOMA DE CALA | E98: ZONA: CRUZ BLANCA PARTE BAJA | F98: 936707747 | G98: 21790332 | H98: =VLOOKUP(G98,consolidado!$A$2:$B$656,2,FALSE) -> #N/A
B99: 97 | C99: MARCOS YATACO PILAR NELLY | D99: CRUZ BLANCA ENTRADA CONDORILLO | E99: ZONA: CRUZ BLANCA PARTE ALTA oruro | F99: 957727000 | G99: 21868131 | H99: =VLOOKUP(G99,consolidado!$A$2:$B$656,2,FALSE) -> #N/A
B100: 98 | C100: DE LA CRUZ MESIAS ALEX GABRIEL | D100: Av Alva Maurtua 144 Cruz blanca | E100: ZONA: CRUZ BLANCA PARTE BAJA | F100: 955737034 | G100: 46981135 | H100: =VLOOKUP(G100,consolidado!$A$2:$B$656,2,FALSE) -> #N/A
B101: 99 | C101: MAGALLANES GARCIA MARITZA | D101: TOMA DE CALA CRUZ BLANCA | E101: ZONA: CRUZ BLANCA PARTE BAJA | F101: 924757716 | G101: 43515540 | H101: =VLOOKUP(G101,consolidado!$A$2:$B$656,2,FALSE) -> #N/A
... B108: 106 | C108: TASAYCO BAUTISTA OSWALDO ERNESTO | D108: Asociación virgen del Carmen mz. A lote 7 (Costado del estadio pasaje girasoles) | E108: ZONA: CRUZ BLANCA PARTE BAJA | F108: 946044404 | G108: 21884554 | H108: =VLOOKUP(G108,consolidado!$A$2:$B$656,2,FALSE) -> #N/A
B109: 107 | C109: TASAYCO MUÑOZ TANIA JAHAYRA | D109: Av. 2 de mayo 299 - Cruz blanca | E109: ZONA: CRUZ BLANCA PARTE ALTA oruro | F109: 945 111 670 | G109: 75473800 | H109: =VLOOKUP(G109,consolidado!$A$2:$B$656,2,FALSE) -> #N/A
B110: 108 | C110: SARAVIA SEBASTIAN VERONICA | D110: psj santa rosa sunampe guayabo cholo | E110: ZONA: SUNAMPE – SAN IGNACIO | F110: 984 964 759 | G110: 43085081 | H110: =VLOOKUP(G110,consolidado!$A$2:$B$656,2,FALSE) -> #N/A
B111: 109 | C111: CLAROS MAGALLANES JERSON JESUS | D111: toma de cala lt 16 | E111: ZONA: CRUZ BLANCA PARTE BAJA | F111: 970 855 964 | G111: 76920562 | H111: =VLOOKUP(G111,consolidado!$A$2:$B$656,2,FALSE) -> #N/A
B112: 110 | C112: NAPA CARBAJAL DE MENESES MARIA ELENA | D112: Calle El carmen 180-cruz blanca | E112: ZONA: CRUZ BLANCA PARTE BAJA | F112: 940 088 604 | G112: 42517738 | H112: =VLOOKUP(G112,consolidado!$A$2:$B$656,2,FALSE) -> #N/A
...

Sheet consolidado
A1: # | B1: CLIENTE | C1: DIRECCIÓN | D1: DISTRITO | E1: ZONA | F1: TELÉFONO | G1: DNI | H1: TIPO
A2: 1 | B2: HUATTA HUATTA FRANCISCO FABIO | C2: AAHH Señor de los Milagros Mz p1 L 16, Quinta etapa | D2: PUEBLO NUEVO | E2: Zona: SrMilagros | F2: 941778098 | G2: 01248667 | H2: F2 | I2: ="('"&B2&"','"&C2&"','"&D2&"','"&E2&"','"&F2&"','"&G2&"','"&H2&"')," -> ('HUATTA HUATTA FRANCISCO FABIO','AAHH Señor de los Milagros Mz p1 L 16, Quinta etapa','PUEBLO NUEVO','Zona: SrMilagros','941778098','01248667','F2'),
A3: 2 | B3: FLOR DEL VALLE RODRIGUEZ GARELLI | C3: Av. alva maurtua lt 05 Cruz Blanca | D3: CHINCHA ALTA | E3: ZONA: CRUZ BLANCA PARTE ALTA oruro | F3: 917638838 | G3: 004039538 | H3: F1 | I3: ="('"&B3&"','"&C3&"','"&D3&"','"&E3&"','"&F3&"','"&G3&"','"&H3&"')," -> ('FLOR DEL VALLE RODRIGUEZ GARELLI','Av. alva maurtua lt 05 Cruz Blanca','CHINCHA ALTA','ZONA: CRUZ BLANCA PARTE ALTA oruro','917638838','004039538','F1'),
A4: 3 | B4: TIMAURE CAMACHO CAROLINA COROMOTO | C4: CL. Santa Teresa 355 Entrada a Sant aFe- Sunampe | D4: SUNAMPE | E4: ZONA: SUNAMPE – SANTA FE | F4: 902253434 | G4: 004377762 | H4: F1 | I4: ="('"&B4&"','"&C4&"','"&D4&"','"&E4&"','"&F4&"','"&G4&"','"&H4&"')," -> ('TIMAURE CAMACHO CAROLINA COROMOTO','CL. Santa Teresa 355 Entrada a Sant aFe- Sunampe','SUNAMPE','ZONA: SUNAMPE – SANTA FE','902253434','004377762','F1'),
A5: 4 | B5: YATACO VIDAL JAIME JUAN | C5: Calle Parada de los amigos 409 - Sunampe | D5: SUNAMPE | E5: ZONA: SUNAMPE – SAN PILPA | F5: 989058641 | G5: 06093318 | H5: F1 | I5: ="('"&B5&"','"&C5&"','"&D5&"','"&E5&"','"&F5&"','"&G5&"','"&H5&"')," -> ('YATACO VIDAL JAIME JUAN','Calle Parada de los amigos 409 - Sunampe','SUNAMPE','ZONA: SUNAMPE – SAN PILPA','989058641','06093318','F1'),
A6: 6 | B6: JANAMPA GOMEZ MAXIMO | C6: Condorillo alto MZ I LT 01 | D6: CHINCHA ALTA | E6: ZONA: CRUZ BLANCA CAMPO | F6: 902102201 | G6: 06567453 | H6: F1 | I6: ="('"&B6&"','"&C6&"','"&D6&"','"&E6&"','"&F6&"','"&G6&"','"&H6&"')," -> ('JANAMPA GOMEZ MAXIMO','Condorillo alto MZ I LT 01','CHINCHA ALTA','ZONA: CRUZ BLANCA CAMPO','902102201','06567453','F1'),
A7: 7 | B7: DE LA CRUZ QUISPE LILIANA | C7: Calle las Nazarenas, S/n Huaca Grande- Sunampe | D7: SUNAMPE | E7: ZONA: SUNAMPE – HUACA GRANDE | F7: 977265651 | G7: 06799544 | H7: F1 | I7: ="('"&B7&"','"&C7&"','"&D7&"','"&E7&"','"&F7&"','"&G7&"','"&H7&"')," -> ('DE LA CRUZ QUISPE LILIANA','Calle las Nazarenas, S/n Huaca Grande- Sunampe','SUNAMPE','ZONA: SUNAMPE – HUACA GRANDE','977265651','06799544','F1'),
A8: 8 | B8: LEVANO DE LA CRUZ FRANCISCA ESTHER | C8: AV. SANTA RITA N°204 (AMERICA) - CHINCHA ALTA | D8: CHINCHA ALTA | E8: ZONA: CHINCHA - PROGRESO | F8: 956 505 830 | G8: 07597465 | H8: F2 | I8: ="('"&B8&"','"&C8&"','"&D8&"','"&E8&"','"&F8&"','"&G8&"','"&H8&"')," -> ('LEVANO DE LA CRUZ FRANCISCA ESTHER','AV. SANTA RITA N°204 (AMERICA) - CHINCHA ALTA','CHINCHA ALTA','ZONA: CHINCHA - PROGRESO','956 505 830','07597465','F2'),
A9: 9 | B9: CONOCC HUAMAN MANUEL MARINO | C9: PSJ. LA PALMA, FUNDO EL NISPERO LT. 05 - SUNAMPE | D9: SUNAMPE | E9: ZONA: SUNAMPE – SAN PILPA | F9: 945 301 046 | G9: 08347575 | H9: F1 | I9: ="('"&B9&"','"&C9&"','"&D9&"','"&E9&"','"&F9&"','"&G9&"','"&H9&"')," -> ('CONOCC HUAMAN MANUEL MARINO','PSJ. LA PALMA, FUNDO EL NISPERO LT. 05 - SUNAMPE','SUNAMPE','ZONA: SUNAMPE – SAN PILPA','945 301 046','08347575','F1'),
A10: 10 | B10: VIOLETA GUTIERREZ GUILLERMO FELICIANO | C10: Av. pachacutec 2645 Cruz Blanca | D10: CHINCHA ALTA | E10: ZONA: CRUZ BLANCA VIRGEN CARMEN | F10: 997588370 | G10: 08998598 | H10: F1 | I10: ="('"&B10&"','"&C10&"','"&D10&"','"&E10&"','"&F10&"','"&G10&"','"&H10&"')," -> ('VIOLETA GUTIERREZ GUILLERMO FELICIANO','Av. pachacutec 2645 Cruz Blanca','CHINCHA ALTA','ZONA: CRUZ BLANCA VIRGEN CARMEN','997588370','08998598','F1'),
A11: 11 | B11: PRIETO LOYOLA REYNALDO | C11: San Juan con San pedro de pilpa - Sunampe | D11: SUNAMPE | E11: ZONA: SUNAMPE – SAN PILPA | F11: 941310699 | G11: 09267192 | H11: F1 | I11: ="('"&B11&"','"&C11&"','"&D11&"','"&E11&"','"&F11&"','"&G11&"','"&H11&"')," -> ('PRIETO LOYOLA REYNALDO','San Juan con San pedro de pilpa - Sunampe','SUNAMPE','ZONA: SUNAMPE – SAN PILPA','941310699','09267192','F1'),
A12: 12 | B12: ARANGO ESCOBAR TEOFILO GENARO | C12: Satelite primaveral, quinta etapa ref: conocido como Hugo Chavez | D12: PUEBLO NUEVO | E12: Zona: SrMilagros | F12: 995719091 | G12: 09436528 | H12: F1 | I12: ="('"&B12&"','"&C12&"','"&D12&"','"&E12&"','"&F12&"','"&G12&"','"&H12&"')," -> ('ARANGO ESCOBAR TEOFILO GENARO','Satelite primaveral, quinta etapa ref: conocido como Hugo Chavez','PUEBLO NUEVO','Zona: SrMilagros','995719091','09436528','F1'),
A13: 14 | B13: BENITES BOCANEGRA FRANCISCO HERMAN | C13: PSJ. SAN JUAN LT. 94A - ALFONSO UGARTE - SUNAMPE | D13: SUNAMPE | E13: ZONA: SUNAMPE – SAN PILPA | F13: 993656810 | G13: 09736546 | H13: F1 | I13: ="('"&B13&"','"&C13&"','"&D13&"','"&E13&"','"&F13&"','"&G13&"','"&H13&"')," -> ('BENITES BOCANEGRA FRANCISCO HERMAN','PSJ. SAN JUAN LT. 94A - ALFONSO UGARTE - SUNAMPE','SUNAMPE','ZONA: SUNAMPE – SAN PILPA','993656810','09736546','F1'),
A14: 15 | B14: RAMOS RIOS MOISES MATEO | C14: Pazo de gomez santa rosa , segunda entrada | D14: SUNAMPE | E14: Zona: Sunampe | F14: 960106705 | G14: 09756783 | H14: F1 | I14: ="('"&B14&"','"&C14&"','"&D14&"','"&E14&"','"&F14&"','"&G14&"','"&H14&"')," -> ('RAMOS RIOS MOISES MATEO','Pazo de gomez santa rosa , segunda entrada','SUNAMPE','Zona: Sunampe','960106705','09756783','F1'),
A15: 16 | B15: ROMERO GARRIAZO JOSE ALBERTO | C15: PSJ. SARAVIA S/N - CERCADO DE GROCIO PRADO | D15: SUNAMPE | E15: ZONA: SUNAMPE – SAN PILPA | F15: 981295133 | G15: 15359111 | H15: F1 | I15: ="('"&B15&"','"&C15&"','"&D15&"','"&E15&"','"&F15&"','"&G15&"','"&H15&"')," -> ('ROMERO GARRIAZO JOSE ALBERTO','PSJ. SARAVIA S/N - CERCADO DE GROCIO PRADO','SUNAMPE','ZONA: SUNAMPE – SAN PILPA','981295133','15359111','F1'),
A16: 17 | B16: PALLIN HUARCAYA CARLOS AURELIO | C16: PSJ. VILLA S/N, CALLE SAN VICENTE DE FERRER - SUNAMPE | D16: SUNAMPE | E16: ZONA: SUNAMPE – SAN PILPA | F16: 918 102 342 | G16: 15359608 | H16: F1 | I16: ="('"&B16&"','"&C16&"','"&D16&"','"&E16&"','"&F16&"','"&G16&"','"&H16&"')," -> ('PALLIN HUARCAYA CARLOS AURELIO','PSJ. VILLA S/N, CALLE SAN VICENTE DE FERRER - SUNAMPE','SUNAMPE','ZONA: SUNAMPE – SAN PILPA','918 102 342','15359608','F1'),
A17: 18 | B17: CAMPOS BARRIOS JUANA MILAGROS | C17: UPIS SAN ANDRES MZ. F - LT. 19 - PUEBLO NUEVO - CHINCHA | D17: PUEBLO NUEVO | E17: ZONA: PUEBLO - TECHO PROPIO | F17: 956 517 578 | G17: 15439628 | H17: F1 | I17: ="('"&B17&"','"&C17&"','"&D17&"','"&E17&"','"&F17&"','"&G17&"','"&H17&"')," -> ('CAMPOS BARRIOS JUANA MILAGROS','UPIS SAN ANDRES MZ. F - LT. 19 - PUEBLO NUEVO - CHINCHA','PUEBLO NUEVO','ZONA: PUEBLO - TECHO PROPIO','956 517 578','15439628','F1'),
A18: 20 | B18: MANUEL YSMAEL YARASCA PURAY | C18: AA.HH. VIRGEN DEL CARMEN MZ A LT 10 - CRUZ BLANCA | D18: CHINCHA ALTA | E18: ZONA: CRUZ BLANCA VIRGEN CARMEN | F18: 950 347 145 | G18: 21519428 | H18: F1 | I18: ="('"&B18&"','"&C18&"','"&D18&"','"&E18&"','"&F18&"','"&G18&"','"&H18&"')," -> ('MANUEL YSMAEL YARASCA PURAY','AA.HH. VIRGEN DEL CARMEN MZ A LT 10 - CRUZ BLANCA','CHINCHA ALTA','ZONA: CRUZ BLANCA VIRGEN CARMEN','950 347 145','21519428','F1'),
A19: 21 | B19: RAMOS AQUIJE EDDY GILMORE | C19: C.P. CONDORILLO ALTO MZ. N LT. 02 - CHINCHA | D19: CHINCHA ALTA | E19: ZONA: CONDORILLO PARTE ALTA | F19: 936 932 786 | G19: 21577420 | H19: F2 | I19: ="('"&B19&"','"&C19&"','"&D19&"','"&E19&"','"&F19&"','"&G19&"','"&H19&"')," -> ('RAMOS AQUIJE EDDY GILMORE','C.P. CONDORILLO ALTO MZ. N LT. 02 - CHINCHA','CHINCHA ALTA','ZONA: CONDORILLO PARTE ALTA','936 932 786','21577420','F2'),
A20: 22 | B20: YATACO GARCIA MOISES | C20: CL. SAN LUIS Nª 139 - CERCADO DE CHINCHA ALTA | D20: CHINCHA ALTA | E20: ZONA: CRUZ BLANCA VIRGEN CARMEN | F20: 944420613 | G20: 21781164 | H20: F1 | I20: ="('"&B20&"','"&C20&"','"&D20&"','"&E20&"','"&F20&"','"&G20&"','"&H20&"')," -> ('YATACO GARCIA MOISES','CL. SAN LUIS Nª 139 - CERCADO DE CHINCHA ALTA','CHINCHA ALTA','ZONA: CRUZ BLANCA VIRGEN CARMEN','944420613','21781164','F1'),
A21: 23 | B21: RIQUELME APOLAYA VDA DE PEREZ GREGORIA ELISA | C21: Av. Melchorita Nº 604 - Grocio Prado | D21: GROCIO PRADO | E21: ZONA: GROCIO - MEJILLONEROS | F21: 956698366 | G21: 21782120 | H21: F1 | I21: ="('"&B21&"','"&C21&"','"&D21&"','"&E21&"','"&F21&"','"&G21&"','"&H21&"')," -> ('RIQUELME APOLAYA VDA DE PEREZ GREGORIA ELISA','Av. Melchorita Nº 604 - Grocio Prado','GROCIO PRADO','ZONA: GROCIO - MEJILLONEROS','956698366','21782120','F1'),
A22: 24 | B22: HERRERA TALLA EDNA CLEMENCIA | C22: AV. UNION SANTA ROSA N110-34 - CRUZ BLANCA | D22: CHINCHA ALTA | E22: ZONA: CRUZ BLANCA CAMPO | F22: 936301541 | G22: 21782325 | H22: F1 | I22: ="('"&B22&"','"&C22&"','"&D22&"','"&E22&"','"&F22&"','"&G22&"','"&H22&"')," -> ('HERRERA TALLA EDNA CLEMENCIA','AV. UNION SANTA ROSA N110-34 - CRUZ BLANCA','CHINCHA ALTA','ZONA: CRUZ BLANCA CAMPO','936301541','21782325','F1'),
A23: 25 | B23: REYES APONTE LUIS MANUEL | C23: CONDORILLO ALTO PRIMERA ENTRADA | D23: CHINCHA ALTA | E23: ZONA: CONDORILLO PARTE BAJA | F23: 936457904 | G23: 21783726 | H23: F1 | I23: ="('"&B23&"','"&C23&"','"&D23&"','"&E23&"','"&F23&"','"&G23&"','"&H23&"')," -> ('REYES APONTE LUIS MANUEL','CONDORILLO ALTO PRIMERA ENTRADA','CHINCHA ALTA','ZONA: CONDORILLO PARTE BAJA','936457904','21783726','F1'),
A24: 26 | B24: CARBAJAL TASAYCO ALBERTO | C24: ENTRADA CONDORILLO PSJ GONZALES PRADA 205 | D24: CHINCHA ALTA | E24: ZONA: CRUZ BLANCA PARTE ALTA oruro | F24: 930 647 571 | G24: 21784064 | H24: F1 | I24: ="('"&B24&"','"&C24&"','"&D24&"','"&E24&"','"&F24&"','"&G24&"','"&H24&"')," -> ('CARBAJAL TASAYCO ALBERTO','ENTRADA CONDORILLO PSJ GONZALES PRADA 205','CHINCHA ALTA','ZONA: CRUZ BLANCA PARTE ALTA oruro','930 647 571','21784064','F1'),
A25: 27 | B25: MAGALLANES ROSSI PAULO FELIX | C25: AV. FATIMA S/N - SUNAMPE | D25: SUNAMPE | E25: ZONA: SUNAMPE – COLEGIO | F25: 942811373 | G25: 21785115 | H25: F1 | I25: ="('"&B25&"','"&C25&"','"&D25&"','"&E25&"','"&F25&"','"&G25&"','"&H25&"')," -> ('MAGALLANES ROSSI PAULO FELIX','AV. FATIMA S/N - SUNAMPE','SUNAMPE','ZONA: SUNAMPE – COLEGIO','942811373','21785115','F1'),
A26: 28 | B26: DE LA CRUZ MENDOZA ROSA ELVIRA | C26: PSJ. 02 DE MAYO Nª 325 - CRUZ BLANCA - CHINCHA ALTA | D26: CHINCHA ALTA | E26: ZONA: CRUZ BLANCA PARTE ALTA oruro | F26: 968 416 588 | G26: 21785244 | H26: F1 | I26: ="('"&B26&"','"&C26&"','"&D26&"','"&E26&"','"&F26&"','"&G26&"','"&H26&"')," -> ('DE LA CRUZ MENDOZA ROSA ELVIRA','PSJ. 02 DE MAYO Nª 325 - CRUZ BLANCA - CHINCHA ALTA','CHINCHA ALTA','ZONA: CRUZ BLANCA PARTE ALTA oruro','968 416 588','21785244','F1'),
A27: 29 | B27: ATUNCAR TASAYCO GILDA ESTHER | C27: SAN PEDRO DE PILPA N514 - SUNAMPE | D27: SUNAMPE | E27: ZONA: SUNAMPE – SAN PILPA | F27: 958608401 | G27: 21786233 | H27: F2 | I27: ="('"&B27&"','"&C27&"','"&D27&"','"&E27&"','"&F27&"','"&G27&"','"&H27&"')," -> ('ATUNCAR TASAYCO GILDA ESTHER','SAN PEDRO DE PILPA N514 - SUNAMPE','SUNAMPE','ZONA: SUNAMPE – SAN PILPA','958608401','21786233','F2'),
A28: 30 | B28: PACHAS MARTINEZ JUANA | C28: Virgen del carmen Mz. I lt. 1 | D28: CHINCHA ALTA | E28: ZONA: CRUZ BLANCA VIRGEN CARMEN | F28: 991 488 690 | G28: 21788723 | H28: F1 | I28: ="('"&B28&"','"&C28&"','"&D28&"','"&E28&"','"&F28&"','"&G28&"','"&H28&"')," -> ('PACHAS MARTINEZ JUANA','Virgen del carmen Mz. I lt. 1','CHINCHA ALTA','ZONA: CRUZ BLANCA VIRGEN CARMEN','991 488 690','21788723','F1'),
A29: 31 | B29: GARCIA DE GARCIA GLADYS | C29: CRUZ BLANCA VIRGEN DEL CARMEN AV TOMA DE CALA | D29: CHINCHA ALTA | E29: ZONA: CRUZ BLANCA PARTE BAJA | F29: 936707747 | G29: 21790332 | H29: F1 | I29: ="('"&B29&"','"&C29&"','"&D29&"','"&E29&"','"&F29&"','"&G29&"','"&H29&"')," -> ('GARCIA DE GARCIA GLADYS','CRUZ BLANCA VIRGEN DEL CARMEN AV TOMA DE CALA','CHINCHA ALTA','ZONA: CRUZ BLANCA PARTE BAJA','936707747','21790332','F1'),
A30: 32 | B30: ELENA EVA LORENZA DURAN BLANCO | C30: CL COLON NRO. PUERTA 279 02 - CERCADO DE CHINCHA ALTA - CHINCHA ALTA | D30: CHINCHA ALTA | E30: ZONA: CHINCHA - AMERICA | F30: 984399198 | G30: 21792478 | H30: F1 | I30: ="('"&B30&"','"&C30&"','"&D30&"','"&E30&"','"&F30&"','"&G30&"','"&H30&"')," -> ('ELENA EVA LORENZA DURAN BLANCO','CL COLON NRO. PUERTA 279 02 - CERCADO DE CHINCHA ALTA - CHINCHA ALTA','CHINCHA ALTA','ZONA: CHINCHA - AMERICA','984399198','21792478','F1'),
A31: 33 | B31: MAGALLANES ORTIZ VICTOR LUIS | C31: CL. EL CARMEN Nª 196, CRUZ BLANCA - CHINCHA ALTA | D31: CHINCHA ALTA | E31: ZONA: CRUZ BLANCA PARTE BAJA | F31: 912074015 | G31: 21794090 | H31: F1 | I31: ="('"&B31&"','"&C31&"','"&D31&"','"&E31&"','"&F31&"','"&G31&"','"&H31&"')," -> ('MAGALLANES ORTIZ VICTOR LUIS','CL. EL CARMEN Nª 196, CRUZ BLANCA - CHINCHA ALTA','CHINCHA ALTA','ZONA: CRUZ BLANCA PARTE BAJA','912074015','21794090','F1'),
A32: 34 | B32: PEREZ HERNANDEZ JORGE ISIDORO | C32: AV. AMERICA N° 533 - INT. 03 - PROGRESO - CHINCHA ALTA | D32: CHINCHA ALTA | E32: ZONA: CHINCHA - PROGRESO | F32: 924422788 | G32: 21794408 | H32: F1 | I32: ="('"&B32&"','"&C32&"','"&D32&"','"&E32&"','"&F32&"','"&G32&"','"&H32&"')," -> ('PEREZ HERNANDEZ JORGE ISIDORO','AV. AMERICA N° 533 - INT. 03 - PROGRESO - CHINCHA ALTA','CHINCHA ALTA','ZONA: CHINCHA - PROGRESO','924422788','21794408','F1'),
A33: 35 | B33: MELO GUERRA ANSELMO | C33: PSJ. SAN MARTIN Nª 474, C.P. MINA DE ORO - SUNAMPE | D33: SUNAMPE | E33: ZONA: SUNAMPE - MINA DE ORO | F33: 904830949 | G33: 21794453 | H33: F1 | I33: ="('"&B33&"','"&C33&"','"&D33&"','"&E33&"','"&F33&"','"&G33&"','"&H33&"')," -> ('MELO GUERRA ANSELMO','PSJ. SAN MARTIN Nª 474, C.P. MINA DE ORO - SUNAMPE','SUNAMPE','ZONA: SUNAMPE - MINA DE ORO','904830949','21794453','F1'),
A34: 36 | B34: DIAZ MAGALLANES SANTOS MANUEL | C34: CRUZ BLANCA VIRGEN DEL CARMEN | D34: CHINCHA ALTA | E34: ZONA: CRUZ BLANCA PARTE BAJA | F34: 925064547 | G34: 21797192 | H34: F1 | I34: ="('"&B34&"','"&C34&"','"&D34&"','"&E34&"','"&F34&"','"&G34&"','"&H34&"')," -> ('DIAZ MAGALLANES SANTOS MANUEL','CRUZ BLANCA VIRGEN DEL CARMEN','CHINCHA ALTA','ZONA: CRUZ BLANCA PARTE BAJA','925064547','21797192','F1'),
A35: 37 | B35: CESPEDES CANELO GLADYS DORA | C35: PSJ. SAN ANTONIO MZ J LT12, ALT. VILLA JULIA - SUNAMPE | D35: SUNAMPE | E35: ZONA: SUNAMPE – VILLA JULIA | F35: 932233737 | G35: 21799902 | H35: F1 | I35: ="('"&B35&"','"&C35&"','"&D35&"','"&E35&"','"&F35&"','"&G35&"','"&H35&"')," -> ('CESPEDES CANELO GLADYS DORA','PSJ. SAN ANTONIO MZ J LT12, ALT. VILLA JULIA - SUNAMPE','SUNAMPE','ZONA: SUNAMPE – VILLA JULIA','932233737','21799902','F1'),
A36: 38 | B36: VILLAVICENCIO GONZALES ORLANDO LUIS | C36: Urb Las Palmeras Mz. D, lote 14, Huaca Grande, Sunampe. | D36: SUNAMPE | E36: ZONA: SUNAMPE – HUACA GRANDE | F36: 955939014 | G36: 21807490 | H36: F1 | I36: ="('"&B36&"','"&C36&"','"&D36&"','"&E36&"','"&F36&"','"&G36&"','"&H36&"')," -> ('VILLAVICENCIO GONZALES ORLANDO LUIS','Urb Las Palmeras Mz. D, lote 14, Huaca Grande, Sunampe.','SUNAMPE','ZONA: SUNAMPE – HUACA GRANDE','955939014','21807490','F1'),
A37: 39 | B37: SALVADOR DE VILLAVICENCIO ANA GLADYS | C37: CONDOMINIO LAS PALMERAS B-29 - C.P. HUACA GRANDE - SUNAMPE | D37: SUNAMPE | E37: ZONA: SUNAMPE – HUACA GRANDE | F37: 955939014 | G37: 21807491 | H37: F1 | I37: ="('"&B37&"','"&C37&"','"&D37&"','"&E37&"','"&F37&"','"&G37&"','"&H37&"')," -> ('SALVADOR DE VILLAVICENCIO ANA GLADYS','CONDOMINIO LAS PALMERAS B-29 - C.P. HUACA GRANDE - SUNAMPE','SUNAMPE','ZONA: SUNAMPE – HUACA GRANDE','955939014','21807491','F1'),
A38: 40 | B38: IBARRA SALAZAR CIRO WILLMAN | C38: URB. JULIO ARBOLEDA MZ. B - LT. 04 - CHINCHA ALTA | D38: SUNAMPE | E38: ZONA: SUNAMPE - MINA DE ORO | F38: 956562524 | G38: 21807868 | H38: F1 | I38: ="('"&B38&"','"&C38&"','"&D38&"','"&E38&"','"&F38&"','"&G38&"','"&H38&"')," -> ('IBARRA SALAZAR CIRO WILLMAN','URB. JULIO ARBOLEDA MZ. B - LT. 04 - CHINCHA ALTA','SUNAMPE','ZONA: SUNAMPE - MINA DE ORO','956562524','21807868','F1'),
A39: 41 | B39: ATUNCAR DE LA CRUZ LUZ MARLENE | C39: Sunampe, Av. Huascar (Casa de pandora 02) | D39: SUNAMPE | E39: ZONA: SUNAMPE – SAN IGNACIO | F39: 965696392 | G39: 21808481 | H39: F1 | I39: ="('"&B39&"','"&C39&"','"&D39&"','"&E39&"','"&F39&"','"&G39&"','"&H39&"')," -> ('ATUNCAR DE LA CRUZ LUZ MARLENE','Sunampe, Av. Huascar (Casa de pandora 02)','SUNAMPE','ZONA: SUNAMPE – SAN IGNACIO','965696392','21808481','F1'),
A40: 42 | B40: AGUILAR HERNANDEZ DE MUCHAYPIÑA MARIA ELIZABETH | C40: URB. LEON DE VIVERO MZ. 04 LT. 07 - PUEBLO NUEVO | D40: PUEBLO NUEVO | E40: ZONA: PUEBLO - SALVADOR | F40: 956 791 396 | G40: 21810864 | H40: F1 | I40: ="('"&B40&"','"&C40&"','"&D40&"','"&E40&"','"&F40&"','"&G40&"','"&H40&"')," -> ('AGUILAR HERNANDEZ DE MUCHAYPIÑA MARIA ELIZABETH','URB. LEON DE VIVERO MZ. 04 LT. 07 - PUEBLO NUEVO','PUEBLO NUEVO','ZONA: PUEBLO - SALVADOR','956 791 396','21810864','F1'),
A41: 43 | B41: CASTILLA VILCHEZ RICARDO ANTONIO | C41: PSJE CASTILLA Nª 268 - C. P. SAN PEDRO DE PILPA - SUNAMPE | D41: SUNAMPE | E41: ZONA: SUNAMPE – SAN PILPA | F41: 933212718 | G41: 21811430 | H41: F1 | I41: ="('"&B41&"','"&C41&"','"&D41&"','"&E41&"','"&F41&"','"&G41&"','"&H41&"')," -> ('CASTILLA VILCHEZ RICARDO ANTONIO','PSJE CASTILLA Nª 268 - C. P. SAN PEDRO DE PILPA - SUNAMPE','SUNAMPE','ZONA: SUNAMPE – SAN PILPA','933212718','21811430','F1'),
A42: 44 | B42: DE LA CRUZ OLIVARES ROSA ALBINA | C42: Av. Alva Maurtua Nº 300 - Cruz Blanca | D42: CHINCHA ALTA | E42: ZONA: CRUZ BLANCA PARTE ALTA oruro | F42: 984786637 | G42: 21811546 | H42: F1 | I42: ="('"&B42&"','"&C42&"','"&D42&"','"&E42&"','"&F42&"','"&G42&"','"&H42&"')," -> ('DE LA CRUZ OLIVARES ROSA ALBINA','Av. Alva Maurtua Nº 300 - Cruz Blanca','CHINCHA ALTA','ZONA: CRUZ BLANCA PARTE ALTA oruro','984786637','21811546','F1'),
A43: 45 | B43: SANCHEZ NAPA ROCIO PATRICIA | C43: AV. ALVA MAURTUA MZ. O LT. 05, PSJ SOTELO - CRUZ BLANCA | D43: CHINCHA ALTA | E43: ZONA: CRUZ BLANCA PARTE ALTA oruro | F43: 967775894 | G43: 21811821 | H43: F1 | I43: ="('"&B43&"','"&C43&"','"&D43&"','"&E43&"','"&F43&"','"&G43&"','"&H43&"')," -> ('SANCHEZ NAPA ROCIO PATRICIA','AV. ALVA MAURTUA MZ. O LT. 05, PSJ SOTELO - CRUZ BLANCA','CHINCHA ALTA','ZONA: CRUZ BLANCA PARTE ALTA oruro','967775894','21811821','F1'),
A44: 46 | B44: ROSA MARIA CAVERO FERNANDEZ | C44: URB. LEON DE VIVERO MZ. 7 LT. 13 - PUEBLO NUEVO | D44: PUEBLO NUEVO | E44: ZONA: PUEBLO - SALVADOR | F44: 943285509 | G44: 21812467 | H44: F2 | I44: ="('"&B44&"','"&C44&"','"&D44&"','"&E44&"','"&F44&"','"&G44&"','"&H44&"')," -> ('ROSA MARIA CAVERO FERNANDEZ','URB. LEON DE VIVERO MZ. 7 LT. 13 - PUEBLO NUEVO','PUEBLO NUEVO','ZONA: PUEBLO - SALVADOR','943285509','21812467','F2'),
A45: 48 | B45: DE LA CRUZ LUYO ALCIDES | C45: AA.HH. EL SALVADOR MZ. F LT. 01 - PUEBLO NUEVO | D45: PUEBLO NUEVO | E45: ZONA: PUEBLO - SALVADOR | F45: 936436485 | G45: 21813235 | H45: F1 | I45: ="('"&B45&"','"&C45&"','"&D45&"','"&E45&"','"&F45&"','"&G45&"','"&H45&"')," -> ('DE LA CRUZ LUYO ALCIDES','AA.HH. EL SALVADOR MZ. F LT. 01 - PUEBLO NUEVO','PUEBLO NUEVO','ZONA: PUEBLO - SALVADOR','936436485','21813235','F1'),
A46: 49 | B46: MILAGRITOS DE JESUS GILARDINO LUY DE REYNAGA | C46: AV. SAN PEDRO DE PILPA NRO. 268 - SUNAMPE | D46: SUNAMPE | E46: ZONA: SUNAMPE – SAN PILPA | F46: 956835450 | G46: 21814474 | H46: F1 | I46: ="('"&B46&"','"&C46&"','"&D46&"','"&E46&"','"&F46&"','"&G46&"','"&H46&"')," -> ('MILAGRITOS DE JESUS GILARDINO LUY DE REYNAGA','AV. SAN PEDRO DE PILPA NRO. 268 - SUNAMPE','SUNAMPE','ZONA: SUNAMPE – SAN PILPA','956835450','21814474','F1'),
A47: 50 | B47: MARIA EMILIA DE LA CRUZ HUASASQUICHE | C47: AVDA LUIS ALVA MAURTUA Nro. Tapa Medidor 01006900 Cercado Chincha Alta CHINCHA ALTA | D47: CHINCHA ALTA | E47: ZONA: CRUZ BLANCA PARTE BAJA | F47: 932437255 | G47: 21814478 | H47: F1 | I47: ="('"&B47&"','"&C47&"','"&D47&"','"&E47&"','"&F47&"','"&G47&"','"&H47&"')," -> ('MARIA EMILIA DE LA CRUZ HUASASQUICHE','AVDA LUIS ALVA MAURTUA Nro. Tapa Medidor 01006900 Cercado Chincha Alta CHINCHA ALTA','CHINCHA ALTA','ZONA: CRUZ BLANCA PARTE BAJA','932437255','21814478','F1'),
A48: 51 | B48: ROJAS MARCELO AQUILES | C48: CL. JORGE CHAVEZ MZ C. - LT. 24 - BARRIO CHACARITA - SUNAMPE | D48: SUNAMPE | E48: ZONA: SUNAMPE – CHACARITA | F48: 998322738 | G48: 21815052 | H48: F2 | I48: ="('"&B48&"','"&C48&"','"&D48&"','"&E48&"','"&F48&"','"&G48&"','"&H48&"')," -> ('ROJAS MARCELO AQUILES','CL. JORGE CHAVEZ MZ C. - LT. 24 - BARRIO CHACARITA - SUNAMPE','SUNAMPE','ZONA: SUNAMPE – CHACARITA','998322738','21815052','F2'),
A49: 52 | B49: HERRERA TALLA JOSE FREDY | C49: AV. UNION SANTA ROSA N109, INT 33 - CRUZ BLANCA | D49: CHINCHA ALTA | E49: ZONA: CRUZ BLANCA CAMPO | F49: 923014014 | G49: 21815108 | H49: F2 | I49: ="('"&B49&"','"&C49&"','"&D49&"','"&E49&"','"&F49&"','"&G49&"','"&H49&"')," -> ('HERRERA TALLA JOSE FREDY','AV. UNION SANTA ROSA N109, INT 33 - CRUZ BLANCA','CHINCHA ALTA','ZONA: CRUZ BLANCA CAMPO','923014014','21815108','F2'),
A50: 53 | B50: COLLACHAGUA TAYPE PATRICIA ESTHER | C50: CL. ROSARIO N° 500 INT. 07 - CERCADO DE CHINCHA - CHINCHA ALTA | D50: PUEBLO NUEVO | E50: ZONA: PUEBLO - TECHO PROPIO | F50: 933513255 | G50: 21815544 | H50: F1 | I50: ="('"&B50&"','"&C50&"','"&D50&"','"&E50&"','"&F50&"','"&G50&"','"&H50&"')," -> ('COLLACHAGUA TAYPE PATRICIA ESTHER','CL. ROSARIO N° 500 INT. 07 - CERCADO DE CHINCHA - CHINCHA ALTA','PUEBLO NUEVO','ZONA: PUEBLO - TECHO PROPIO','933513255','21815544','F1'),
A51: 54 | B51: YATACO GARCIA MARIA SANTOS | C51: PSJ. DOS DE MAYO S/N - CRUZ BLANCA - CHINCHA | D51: CHINCHA ALTA | E51: ZONA: CRUZ BLANCA PARTE ALTA oruro | F51: 965696054 | G51: 21815949 | H51: F1 | I51: ="('"&B51&"','"&C51&"','"&D51&"','"&E51&"','"&F51&"','"&G51&"','"&H51&"')," -> ('YATACO GARCIA MARIA SANTOS','PSJ. DOS DE MAYO S/N - CRUZ BLANCA - CHINCHA','CHINCHA ALTA','ZONA: CRUZ BLANCA PARTE ALTA oruro','965696054','21815949','F1'),
A52: 55 | B52: PEVE GUTIERREZ JHON ROBINSON | C52: Avenida principal mz A Lt 11 , centro Poblado Condorillo Alto Ref: Por la bodega Charito | D52: CHINCHA ALTA | E52: ZONA: CONDORILLO PARTE ALTA | F52: 971 906 846 | G52: 21817739 | H52: F1 | I52: ="('"&B52&"','"&C52&"','"&D52&"','"&E52&"','"&F52&"','"&G52&"','"&H52&"')," -> ('PEVE GUTIERREZ JHON ROBINSON','Avenida principal mz A Lt 11 , centro Poblado Condorillo Alto Ref: Por la bodega Charito','CHINCHA ALTA','ZONA: CONDORILLO PARTE ALTA','971 906 846','21817739','F1'),
A53: 56 | B53: CASTILLON CHUQUISPUMA LIZANDRO HERCULES | C53: UPIS EL TREBOL MZ. G - LOTE 22 - PUEBLO NUEVO | D53: PUEBLO NUEVO | E53: ZONA: PUEBLO - LAS AMERICAS | F53: 978934930 | G53: 21818918 | H53: F1 | I53: ="('"&B53&"','"&C53&"','"&D53&"','"&E53&"','"&F53&"','"&G53&"','"&H53&"')," -> ('CASTILLON CHUQUISPUMA LIZANDRO HERCULES','UPIS EL TREBOL MZ. G - LOTE 22 - PUEBLO NUEVO','PUEBLO NUEVO','ZONA: PUEBLO - LAS AMERICAS','978934930','21818918','F1'),
A54: 57 | B54: FERNANDEZ MEZA HEBER ANDER | C54: AV. PARAISO NRO. PUERTA 496 - C.P. LOMO LARGO - SUNAMPE | D54: SUNAMPE | E54: ZONA: SUNAMPE – PARAISO | F54: 902779650 | G54: 21819087 | H54: F1 | I54: ="('"&B54&"','"&C54&"','"&D54&"','"&E54&"','"&F54&"','"&G54&"','"&H54&"')," -> ('FERNANDEZ MEZA HEBER ANDER','AV. PARAISO NRO. PUERTA 496 - C.P. LOMO LARGO - SUNAMPE','SUNAMPE','ZONA: SUNAMPE – PARAISO','902779650','21819087','F1'),
A55: 58 | B55: SARAVIA DE YATACO MARITSA YSABEL | C55: San Pedro de Pilpa - PSJE SAN BLAS Nro.Lote 09 Sunampe | D55: SUNAMPE | E55: ZONA: SUNAMPE – SAN PILPA | F55: 922706526 | G55: 21819456 | H55: F1 | I55: ="('"&B55&"','"&C55&"','"&D55&"','"&E55&"','"&F55&"','"&G55&"','"&H55&"')," -> ('SARAVIA DE YATACO MARITSA YSABEL','San Pedro de Pilpa - PSJE SAN BLAS Nro.Lote 09 Sunampe','SUNAMPE','ZONA: SUNAMPE – SAN PILPA','922706526','21819456','F1'),
A56: 59 | B56: ANCHANTE BOADA IVAN MOISES | C56: Prolongación sant domingo #170 chincha baja | D56: TAMBO DE MORA | E56: Zona: Tambo de Mora 1 | F56: 923288466 | G56: 21824486 | H56: F2 | I56: ="('"&B56&"','"&C56&"','"&D56&"','"&E56&"','"&F56&"','"&G56&"','"&H56&"')," -> ('ANCHANTE BOADA IVAN MOISES','Prolongación sant domingo #170 chincha baja','TAMBO DE MORA','Zona: Tambo de Mora 1','923288466','21824486','F2'),
A57: 60 | B57: SANABRIA CONISLLA ERLINDA SONIA | C57: Upis keyko Sofia Mz ñ Lt 20 -Salvador | D57: PUEBLO NUEVO | E57: ZONA: PUEBLO - SALVADOR | F57: 972 027 085 | G57: 21829438 | H57: F1 | I57: ="('"&B57&"','"&C57&"','"&D57&"','"&E57&"','"&F57&"','"&G57&"','"&H57&"')," -> ('SANABRIA CONISLLA ERLINDA SONIA','Upis keyko Sofia Mz ñ Lt 20 -Salvador','PUEBLO NUEVO','ZONA: PUEBLO - SALVADOR','972 027 085','21829438','F1'),
A58: 61 | B58: CASTILLA HUAROTE FELIX | C58: Av. Melchorita 607 - Grocio Prado | D58: GROCIO PRADO | E58: ZONA: GROCIO - EL PORVENIR | F58: 914853211 | G58: 21830221 | H58: F1 | I58: ="('"&B58&"','"&C58&"','"&D58&"','"&E58&"','"&F58&"','"&G58&"','"&H58&"')," -> ('CASTILLA HUAROTE FELIX','Av. Melchorita 607 - Grocio Prado','GROCIO PRADO','ZONA: GROCIO - EL PORVENIR','914853211','21830221','F1'),
A59: 66 | B59: MORON RONCEROS ADALBERTO GUILLERMO | C59: AV. EL PORVENIR LOTE 30(CASA DE 2 PISOS, COSTADO DE UNA TIENDA) | D59: GROCIO PRADO | E59: ZONA: GROCIO - EL PORVENIR | F59: 933142570 | G59: 21838938 | H59: F1 | I59: ="('"&B59&"','"&C59&"','"&D59&"','"&E59&"','"&F59&"','"&G59&"','"&H59&"')," -> ('MORON RONCEROS ADALBERTO GUILLERMO','AV. EL PORVENIR LOTE 30(CASA DE 2 PISOS, COSTADO DE UNA TIENDA)','GROCIO PRADO','ZONA: GROCIO - EL PORVENIR','933142570','21838938','F1'),
A60: 67 | B60: CANCHARI QUISPE JHONY ANGEL | C60: PSJE SAN FRANCISCO MZ. X LT. 8 - C.P. SAN IGNACIO - SUNAMPE | D60: SUNAMPE | E60: ZONA: SUNAMPE – SAN IGNACIO | F60: 963 847 560 | G60: 21845027 | H60: F1 | I60: ="('"&B60&"','"&C60&"','"&D60&"','"&E60&"','"&F60&"','"&G60&"','"&H60&"')," -> ('CANCHARI QUISPE JHONY ANGEL','PSJE SAN FRANCISCO MZ. X LT. 8 - C.P. SAN IGNACIO - SUNAMPE','SUNAMPE','ZONA: SUNAMPE – SAN IGNACIO','963 847 560','21845027','F1'),
A61: 68 | B61: TASAYCO GARCIA DANIEL | C61: Av San Francisco 117 sunampe | D61: SUNAMPE | E61: ZONA: SUNAMPE – SAN IGNACIO | F61: 922771211 | G61: 21845817 | H61: F1 | I61: ="('"&B61&"','"&C61&"','"&D61&"','"&E61&"','"&F61&"','"&G61&"','"&H61&"')," -> ('TASAYCO GARCIA DANIEL','Av San Francisco 117 sunampe','SUNAMPE','ZONA: SUNAMPE – SAN IGNACIO','922771211','21845817','F1'),
A62: 69 | B62: PACHAS SANCHEZ DORIS MARLENE | C62: Av san jose 29 - huaca grande | D62: SUNAMPE | E62: ZONA: SUNAMPE – HUACA GRANDE | F62: 993448961 | G62: 21845970 | H62: F1 | I62: ="('"&B62&"','"&C62&"','"&D62&"','"&E62&"','"&F62&"','"&G62&"','"&H62&"')," -> ('PACHAS SANCHEZ DORIS MARLENE','Av san jose 29 - huaca grande','SUNAMPE','ZONA: SUNAMPE – HUACA GRANDE','993448961','21845970','F1'),
A63: 72 | B63: CRISOSTOMO CUELLAR ARNALDO | C63: PSJ. SANTA ROSA S/N - CRUZ BLANCA | D63: CHINCHA ALTA | E63: ZONA: CRUZ BLANCA PARTE ALTA oruro | F63: 955017366 | G63: 21846116 | H63: F1 | I63: ="('"&B63&"','"&C63&"','"&D63&"','"&E63&"','"&F63&"','"&G63&"','"&H63&"')," -> ('CRISOSTOMO CUELLAR ARNALDO','PSJ. SANTA ROSA S/N - CRUZ BLANCA','CHINCHA ALTA','ZONA: CRUZ BLANCA PARTE ALTA oruro','955017366','21846116','F1'),
A64: 73 | B64: PACHAS SANCHEZ LUIS ARMANDO | C64: AV. EMANCIPACIÓN, PSJE. GUADALUPE Nª 12 - C.P. HUACA GRANDE - SUNAMPE | D64: SUNAMPE | E64: ZONA: SUNAMPE – COLEGIO | F64: 947146086 | G64: 21846189 | H64: F1 | I64: ="('"&B64&"','"&C64&"','"&D64&"','"&E64&"','"&F64&"','"&G64&"','"&H64&"')," -> ('PACHAS SANCHEZ LUIS ARMANDO','AV. EMANCIPACIÓN, PSJE. GUADALUPE Nª 12 - C.P. HUACA GRANDE - SUNAMPE','SUNAMPE','ZONA: SUNAMPE – COLEGIO','947146086','21846189','F1'),
A65: 74 | B65: ROSAS ROJAS JAVIER ELMER | C65: CALLE NAZARENO N° 33 - SUNAMPE | D65: SUNAMPE | E65: ZONA: SUNAMPE – HUACA GRANDE | F65: 956946577 | G65: 21846225 | H65: F1 | I65: ="('"&B65&"','"&C65&"','"&D65&"','"&E65&"','"&F65&"','"&G65&"','"&H65&"')," -> ('ROSAS ROJAS JAVIER ELMER','CALLE NAZARENO N° 33 - SUNAMPE','SUNAMPE','ZONA: SUNAMPE – HUACA GRANDE','956946577','21846225','F1'),
A66: 75 | B66: NAPA CRISOSTOMO RUBEN BAUTISTA | C66: Av. San pedro de pilpa 133 - Lomo largo - Sunampe | D66: SUNAMPE | E66: ZONA: SUNAMPE – SAN PILPA | F66: 902874390 | G66: 21846318 | H66: F1 | I66: ="('"&B66&"','"&C66&"','"&D66&"','"&E66&"','"&F66&"','"&G66&"','"&H66&"')," -> ('NAPA CRISOSTOMO RUBEN BAUTISTA','Av. San pedro de pilpa 133 - Lomo largo - Sunampe','SUNAMPE','ZONA: SUNAMPE – SAN PILPA','902874390','21846318','F1'),
A67: 77 | B67: CRISOSTOMO CUELLA LUIS ALFONSO | C67: A.v Los Proceres s/n -SUNAMPE | D67: SUNAMPE | E67: ZONA: SUNAMPE – COLEGIO | F67: 949645226 | G67: 21846794 | H67: F1 | I67: ="('"&B67&"','"&C67&"','"&D67&"','"&E67&"','"&F67&"','"&G67&"','"&H67&"')," -> ('CRISOSTOMO CUELLA LUIS ALFONSO','A.v Los Proceres s/n -SUNAMPE','SUNAMPE','ZONA: SUNAMPE – COLEGIO','949645226','21846794','F1'),
A68: 78 | B68: ROJAS BACIGALUPO CESAR ANTONIO | C68: CL. 09 DE DICIEMBRE N° 151, CERCADO DE SUNAMPE | D68: SUNAMPE | E68: ZONA: SUNAMPE – SIMON | F68: 956 064 829 | G68: 21847095 | H68: F1 | I68: ="('"&B68&"','"&C68&"','"&D68&"','"&E68&"','"&F68&"','"&G68&"','"&H68&"')," -> ('ROJAS BACIGALUPO CESAR ANTONIO','CL. 09 DE DICIEMBRE N° 151, CERCADO DE SUNAMPE','SUNAMPE','ZONA: SUNAMPE – SIMON','956 064 829','21847095','F1'),
A69: 79 | B69: ROJAS BACIGALUPO CARMELA LEONOR | C69: Av.Nazarenas N 62 Huaca Grande | D69: SUNAMPE | E69: ZONA: SUNAMPE – HUACA GRANDE | F69: 950902644 | G69: 21847118 | H69: F1 | I69: ="('"&B69&"','"&C69&"','"&D69&"','"&E69&"','"&F69&"','"&G69&"','"&H69&"')," -> ('ROJAS BACIGALUPO CARMELA LEONOR','Av.Nazarenas N 62 Huaca Grande','SUNAMPE','ZONA: SUNAMPE – HUACA GRANDE','950902644','21847118','F1'),
A70: 80 | B70: CRISOSTOMO RIVADENEYRA GLADYS | C70: AV. SAN ANTONIO, PSJ. 58 PUERTA N°165 - SUNAMPE | D70: SUNAMPE | E70: ZONA: SUNAMPE – SANTA ROSA | F70: 912 344 640 | G70: 21847790 | H70: F1 | I70: ="('"&B70&"','"&C70&"','"&D70&"','"&E70&"','"&F70&"','"&G70&"','"&H70&"')," -> ('CRISOSTOMO RIVADENEYRA GLADYS','AV. SAN ANTONIO, PSJ. 58 PUERTA N°165 - SUNAMPE','SUNAMPE','ZONA: SUNAMPE – SANTA ROSA','912 344 640','21847790','F1'),
A71: 82 | B71: ALMEYDA DE NAPA MARGARITA VICTORIA | C71: Av. paraíso - Lomo Largo - Sunampe ref: A 1 cuadra del hostal “El otro Sitio” | D71: SUNAMPE | E71: ZONA: SUNAMPE – PARAISO | F71: 965189450 | G71: 21848813 | H71: F1 | I71: ="('"&B71&"','"&C71&"','"&D71&"','"&E71&"','"&F71&"','"&G71&"','"&H71&"')," -> ('ALMEYDA DE NAPA MARGARITA VICTORIA','Av. paraíso - Lomo Largo - Sunampe ref: A 1 cuadra del hostal “El otro Sitio”','SUNAMPE','ZONA: SUNAMPE – PARAISO','965189450','21848813','F1'),
A72: 83 | B72: ISABEL LEONOR MELO VDA DE ALMEYDA | C72: AV. PARAISO N° 49 - C.P. LOMO LARGO - SUNAMPE | D72: SUNAMPE | E72: ZONA: SUNAMPE – SAN PILPA | F72: 967224348 | G72: 21849130 | H72: F1 | I72: ="('"&B72&"','"&C72&"','"&D72&"','"&E72&"','"&F72&"','"&G72&"','"&H72&"')," -> ('ISABEL LEONOR MELO VDA DE ALMEYDA','AV. PARAISO N° 49 - C.P. LOMO LARGO - SUNAMPE','SUNAMPE','ZONA: SUNAMPE – SAN PILPA','967224348','21849130','F1'),
A73: 84 | B73: ROJAS PACHAS JACINTO | C73: PASO DE GOMEZ Nº140 - SUNAMPE | D73: SUNAMPE | E73: ZONA: SUNAMPE – SANTA ROSA | F73: 997007429 | G73: 21849411 | H73: F1 | I73: ="('"&B73&"','"&C73&"','"&D73&"','"&E73&"','"&F73&"','"&G73&"','"&H73&"')," -> ('ROJAS PACHAS JACINTO','PASO DE GOMEZ Nº140 - SUNAMPE','SUNAMPE','ZONA: SUNAMPE – SANTA ROSA','997007429','21849411','F1'),
A74: 85 | B74: TORRES AVALOS ALEJANDRO | C74: AV. HUASCAR 130 - SAN IGNACIO- SUNAMPE REF PLAZUELA DE SAN IGNACIO 1 CDA ADELANTE | D74: SUNAMPE | E74: ZONA: SUNAMPE – SAN IGNACIO | F74: 998232755 | G74: 21849573 | H74: F1 | I74: ="('"&B74&"','"&C74&"','"&D74&"','"&E74&"','"&F74&"','"&G74&"','"&H74&"')," -> ('TORRES AVALOS ALEJANDRO','AV. HUASCAR 130 - SAN IGNACIO- SUNAMPE REF PLAZUELA DE SAN IGNACIO 1 CDA ADELANTE','SUNAMPE','ZONA: SUNAMPE – SAN IGNACIO','998232755','21849573','F1'),
A75: 86 | B75: ALMEYDA SANCHEZ PABLO LUIS | C75: AV. PARAISO N° 21 - LOMO LARGO - SUNAMPE | D75: SUNAMPE | E75: ZONA: SUNAMPE – PARAISO | F75: 952354023 | G75: 21850170 | H75: F1 | I75: ="('"&B75&"','"&C75&"','"&D75&"','"&E75&"','"&F75&"','"&G75&"','"&H75&"')," -> ('ALMEYDA SANCHEZ PABLO LUIS ','AV. PARAISO N° 21 - LOMO LARGO - SUNAMPE','SUNAMPE','ZONA: SUNAMPE – PARAISO','952354023','21850170','F1'),
A76: 87 | B76: DE LA CRUZ QUISPE VICTORIA YSABEL | C76: AV. FATIMA N° 373 - SUNAMPE | D76: SUNAMPE | E76: ZONA: SUNAMPE – HUACA GRANDE | F76: 997067532 | G76: 21850270 | H76: F1 | I76: ="('"&B76&"','"&C76&"','"&D76&"','"&E76&"','"&F76&"','"&G76&"','"&H76&"')," -> ('DE LA CRUZ QUISPE VICTORIA YSABEL','AV. FATIMA N° 373 - SUNAMPE','SUNAMPE','ZONA: SUNAMPE – HUACA GRANDE','997067532','21850270','F1'),
A77: 88 | B77: DE LA CRUZ PACHAS PEDRO ENRIQUE | C77: PSJE. PASO DE GOMEZ Nª 111-10C - C.P. HUACA GRANDE - SUNAMPE | D77: SUNAMPE | E77: ZONA: SUNAMPE – SANTA ROSA | F77: 906071409 | G77: 21850623 | H77: F1 | I77: ="('"&B77&"','"&C77&"','"&D77&"','"&E77&"','"&F77&"','"&G77&"','"&H77&"')," -> ('DE LA CRUZ PACHAS PEDRO ENRIQUE','PSJE. PASO DE GOMEZ Nª 111-10C - C.P. HUACA GRANDE - SUNAMPE','SUNAMPE','ZONA: SUNAMPE – SANTA ROSA','906071409','21850623','F1'),
A78: 89 | B78: ALMEYDA SOLARI BERTHA GLADYS | C78: CALLE TUPAC AMARU Nª 395 - SUNAMPE (Ref. Espalda de la Munic) | D78: SUNAMPE | E78: ZONA: SUNAMPE – SIMON | F78: 948 643 610 | G78: 21851052 | H78: F1 | I78: ="('"&B78&"','"&C78&"','"&D78&"','"&E78&"','"&F78&"','"&G78&"','"&H78&"')," -> ('ALMEYDA SOLARI BERTHA GLADYS','CALLE TUPAC AMARU Nª 395 - SUNAMPE (Ref. Espalda de la Munic)','SUNAMPE','ZONA: SUNAMPE – SIMON','948 643 610','21851052','F1'),
A79: 90 | B79: SAENZ MAGALLANES JULIO CESAR | C79: CALLE LIMA 349- Sunampe (A DOS PUERTAS DE LA POLLERÍA AJÍ SECO) | D79: SUNAMPE | E79: ZONA: SUNAMPE – CALLE LIMA | F79: 944121137 | G79: 21851670 | H79: F1 | I79: ="('"&B79&"','"&C79&"','"&D79&"','"&E79&"','"&F79&"','"&G79&"','"&H79&"')," -> ('SAENZ MAGALLANES JULIO CESAR','CALLE LIMA 349- Sunampe (A DOS PUERTAS DE LA POLLERÍA AJÍ SECO)','SUNAMPE','ZONA: SUNAMPE – CALLE LIMA','944121137','21851670','F1'),
A80: 91 | B80: CASACHAGUA LARA LILIANA ALICIA | C80: AV. JOSE SANTOS CHOCANO N155 - LOMO LARGO - SUNAMPE | D80: SUNAMPE | E80: ZONA: SUNAMPE – SAN PILPA | F80: 928270969 | G80: 21851781 | H80: F1 | I80: ="('"&B80&"','"&C80&"','"&D80&"','"&E80&"','"&F80&"','"&G80&"','"&H80&"')," -> ('CASACHAGUA LARA LILIANA ALICIA','AV. JOSE SANTOS CHOCANO N155 - LOMO LARGO - SUNAMPE','SUNAMPE','ZONA: SUNAMPE – SAN PILPA','928270969','21851781','F1'),
A81: 92 | B81: ALFONSO TORRES GREGORIO ALFREDO | C81: AV. ALFONSO UGARTE N° 544 - SAN PEDRO DE PILPA - SUNAMPE | D81: SUNAMPE | E81: ZONA: SUNAMPE – SAN PILPA | F81: 954052720 | G81: 21852100 | H81: F1 | I81: ="('"&B81&"','"&C81&"','"&D81&"','"&E81&"','"&F81&"','"&G81&"','"&H81&"')," -> ('ALFONSO TORRES GREGORIO ALFREDO','AV. ALFONSO UGARTE N° 544 - SAN PEDRO DE PILPA - SUNAMPE','SUNAMPE','ZONA: SUNAMPE – SAN PILPA','954052720','21852100','F1'),
A82: 93 | B82: GONZALES PEÑA ANA YSABEL | C82: AV.SANTA ROSA 146 SUNAMPE | D82: SUNAMPE | E82: ZONA: SUNAMPE – SANTA ROSA | F82: 933227205 | G82: 21852326 | H82: F1 | I82: ="('"&B82&"','"&C82&"','"&D82&"','"&E82&"','"&F82&"','"&G82&"','"&H82&"')," -> ('GONZALES PEÑA ANA YSABEL','AV.SANTA ROSA 146 SUNAMPE','SUNAMPE','ZONA: SUNAMPE – SANTA ROSA','933227205','21852326','F1'),
A83: 94 | B83: MENESES CANELO LUIS NICOLAS | C83: calle muelle 227 tambo de mora | D83: TAMBO DE MORA | E83: Zona: Tambo de Mora 2 | F83: 994281157 | G83: 21854034 | H83: F2 | I83: ="('"&B83&"','"&C83&"','"&D83&"','"&E83&"','"&F83&"','"&G83&"','"&H83&"')," -> ('MENESES CANELO LUIS NICOLAS','calle muelle 227 tambo de mora','TAMBO DE MORA','Zona: Tambo de Mora 2','994281157','21854034','F2'),
A84: 95 | B84: CHALA MARCHAN FANNY CAROL | C84: Psj jazmin #105 - Tambo de Mora Ref: Frente a la Policia nacion de tambo de mora | D84: TAMBO DE MORA | E84: No especificado | F84: 990519702 | G84: 21854135 | H84: F1 | I84: ="('"&B84&"','"&C84&"','"&D84&"','"&E84&"','"&F84&"','"&G84&"','"&H84&"')," -> ('CHALA MARCHAN FANNY CAROL','Psj jazmin #105 - Tambo de Mora Ref: Frente a la Policia nacion de tambo de mora','TAMBO DE MORA','No especificado','990519702','21854135','F1'),
A85: 97 | B85: DE LA CRUZ MANRIQUE NOLBERTO FLORECINDO | C85: calle San Vicente Ferrer 520 Sunampe | D85: SUNAMPE | E85: ZONA: SUNAMPE – SAN PILPA | F85: 938429070 | G85: 21854378 | H85: F2 | I85: ="('"&B85&"','"&C85&"','"&D85&"','"&E85&"','"&F85&"','"&G85&"','"&H85&"')," -> ('DE LA CRUZ MANRIQUE NOLBERTO FLORECINDO','calle San Vicente Ferrer 520 Sunampe','SUNAMPE','ZONA: SUNAMPE – SAN PILPA','938429070','21854378','F2'),
A86: 98 | B86: ESPINOZA MUÑOZ LILIANA LASTENIA | C86: Av. San marcelo 158 (Villa Julia) - Sunampe | D86: SUNAMPE | E86: ZONA: SUNAMPE – VILLA JULIA | F86: 922393873 | G86: 21854605 | H86: F1 | I86: ="('"&B86&"','"&C86&"','"&D86&"','"&E86&"','"&F86&"','"&G86&"','"&H86&"')," -> ('ESPINOZA MUÑOZ LILIANA LASTENIA','Av. San marcelo 158 (Villa Julia) - Sunampe','SUNAMPE','ZONA: SUNAMPE – VILLA JULIA','922393873','21854605','F1'),
A87: 99 | B87: LOPEZ MATEO SONIA ROSA | C87: Calle Grau 168 lomo largo | D87: SUNAMPE | E87: ZONA: SUNAMPE – PARAISO | F87: 953619455 | G87: 21854655 | H87: F1 | I87: ="('"&B87&"','"&C87&"','"&D87&"','"&E87&"','"&F87&"','"&G87&"','"&H87&"')," -> ('LOPEZ MATEO SONIA ROSA','Calle Grau 168 lomo largo','SUNAMPE','ZONA: SUNAMPE – PARAISO','953619455','21854655','F1'),
A88: 100 | B88: ALMEYDA GARCIA ABEL ARTURO | C88: Calle Grau 108 - Lomo Largo - Sunampe | D88: SUNAMPE | E88: ZONA: SUNAMPE – PARAISO | F88: 914013935 | G88: 21854743 | H88: F1 | I88: ="('"&B88&"','"&C88&"','"&D88&"','"&E88&"','"&F88&"','"&G88&"','"&H88&"')," -> ('ALMEYDA GARCIA ABEL ARTURO','Calle Grau 108 - Lomo Largo - Sunampe','SUNAMPE','ZONA: SUNAMPE – PARAISO','914013935','21854743','F1'),
A89: 101 | B89: CESAR AGUSTO ROJAS RAMOS | C89: AV. FATIMA MZ. I - LT. 01 - SUNAMPE | D89: SUNAMPE | E89: ZONA: SUNAMPE – HUACA GRANDE | F89: 968682700 | G89: 21854794 | H89: F2 | I89: ="('"&B89&"','"&C89&"','"&D89&"','"&E89&"','"&F89&"','"&G89&"','"&H89&"')," -> ('CESAR AGUSTO ROJAS RAMOS','AV. FATIMA MZ. I - LT. 01 - SUNAMPE','SUNAMPE','ZONA: SUNAMPE – HUACA GRANDE','968682700','21854794','F2'),
A90: 102 | B90: LAZARO CANCHARI NESTOR BALVIS | C90: C.P. CONDORILLO ALTO MZ L LT 10 - CHINCHA | D90: CHINCHA ALTA | E90: ZONA: CONDORILLO PARTE ALTA | F90: 910925866 | G90: 21856980 | H90: F1 | I90: ="('"&B90&"','"&C90&"','"&D90&"','"&E90&"','"&F90&"','"&G90&"','"&H90&"')," -> ('LAZARO CANCHARI NESTOR BALVIS','C.P. CONDORILLO ALTO MZ L LT 10 - CHINCHA','CHINCHA ALTA','ZONA: CONDORILLO PARTE ALTA','910925866','21856980','F1'),
A91: 103 | B91: HUAMAN AGUIRRE TEODORA REVECA | C91: AA.HH. LAS ROCAS MZ. F - LT. 06 - PUEBLO NUEVO | D91: PUEBLO NUEVO | E91: ZONA: PUEBLO - SATELITE - ROCAS | F91: 914066332 | G91: 21857342 | H91: F1 | I91: ="('"&B91&"','"&C91&"','"&D91&"','"&E91&"','"&F91&"','"&G91&"','"&H91&"')," -> ('HUAMAN AGUIRRE TEODORA REVECA','AA.HH. LAS ROCAS MZ. F - LT. 06 - PUEBLO NUEVO','PUEBLO NUEVO','ZONA: PUEBLO - SATELITE - ROCAS','914066332','21857342','F1'),
A92: 105 | B92: VELARDE ORTIZ SANTA ANGELICA | C92: AA.HH. EL MILAGRO DE SAN JUDAS TADEO MZ. D - LT. 8 - SUNAMPE | D92: SUNAMPE | E92: ZONA: SUNAMPE - MINA DE ORO | F92: 922 053 311 | G92: 21857534 | H92: F1 | I92: ="('"&B92&"','"&C92&"','"&D92&"','"&E92&"','"&F92&"','"&G92&"','"&H92&"')," -> ('VELARDE ORTIZ SANTA ANGELICA','AA.HH. EL MILAGRO DE SAN JUDAS TADEO MZ. D - LT. 8 - SUNAMPE','SUNAMPE','ZONA: SUNAMPE - MINA DE ORO','922 053 311','21857534','F1'),
A93: 106 | B93: CASTRO AVALOS LUIS FERNANDO | C93: AA.HH. EL SALVADOR MZ. N LT. 06 - PUEBLO NUEVO | D93: PUEBLO NUEVO | E93: ZONA: PUEBLO - SALVADOR | F93: 910942498 | G93: 21859181 | H93: F1 | I93: ="('"&B93&"','"&C93&"','"&D93&"','"&E93&"','"&F93&"','"&G93&"','"&H93&"')," -> ('CASTRO AVALOS LUIS FERNANDO','AA.HH. EL SALVADOR MZ. N LT. 06 - PUEBLO NUEVO','PUEBLO NUEVO','ZONA: PUEBLO - SALVADOR','910942498','21859181','F1'),
A94: 107 | B94: TORRES HUAMAN MARIA ISABEL | C94: psj. primavera 116 cruz blanca | D94: CHINCHA ALTA | E94: ZONA: CRUZ BLANCA CAMPO | F94: 904612007 | G94: 21859806 | H94: F1 | I94: ="('"&B94&"','"&C94&"','"&D94&"','"&E94&"','"&F94&"','"&G94&"','"&H94&"')," -> ('TORRES HUAMAN MARIA ISABEL','psj. primavera 116 cruz blanca','CHINCHA ALTA','ZONA: CRUZ BLANCA CAMPO','904612007','21859806','F1'),
A95: 108 | B95: CHUQUISPUMA PEVE JUANA | C95: C.P. Condorillo alto Mz. O lt. 13 | D95: CHINCHA ALTA | E95: ZONA: CONDORILLO PARTE ALTA | F95: 961760053 | G95: 21859950 | H95: F1 | I95: ="('"&B95&"','"&C95&"','"&D95&"','"&E95&"','"&F95&"','"&G95&"','"&H95&"')," -> ('CHUQUISPUMA PEVE JUANA','C.P. Condorillo alto Mz. O lt. 13','CHINCHA ALTA','ZONA: CONDORILLO PARTE ALTA','961760053','21859950','F1'),
A96: 110 | B96: HERRERA CASAS DE CHINCHAY MARIA ANTONIETA | C96: Calle el Carmen Nº 163 - Cruz Blanca | D96: CHINCHA ALTA | E96: ZONA: CRUZ BLANCA PARTE BAJA | F96: 992870887 | G96: 21860894 | H96: F1 | I96: ="('"&B96&"','"&C96&"','"&D96&"','"&E96&"','"&F96&"','"&G96&"','"&H96&"')," -> ('HERRERA CASAS DE CHINCHAY MARIA ANTONIETA','Calle el Carmen Nº 163 - Cruz Blanca','CHINCHA ALTA','ZONA: CRUZ BLANCA PARTE BAJA','992870887','21860894','F1'),
A97: 111 | B97: GARCIA LY FRIEDA VERONICA | C97: Carretera Sunampe 351 pasando San Ignacio | D97: SUNAMPE | E97: ZONA: SUNAMPE – SAN IGNACIO | F97: 956319825 | G97: 21861508 | H97: F1 | I97: ="('"&B97&"','"&C97&"','"&D97&"','"&E97&"','"&F97&"','"&G97&"','"&H97&"')," -> ('GARCIA LY FRIEDA VERONICA','Carretera Sunampe 351 pasando San Ignacio','SUNAMPE','ZONA: SUNAMPE – SAN IGNACIO','956319825','21861508','F1'),
A98: 112 | B98: BALLENAS DELGADO ANA ETELVINA | C98: CONDOMINIO LOS SAUCES MZ. D LT. 02 - SUNAMPE | D98: SUNAMPE | E98: ZONA: SUNAMPE – SIMON | F98: 917289473 | G98: 21861580 | H98: F1 | I98: ="('"&B98&"','"&C98&"','"&D98&"','"&E98&"','"&F98&"','"&G98&"','"&H98&"')," -> ('BALLENAS DELGADO ANA ETELVINA','CONDOMINIO LOS SAUCES MZ. D LT. 02 - SUNAMPE','SUNAMPE','ZONA: SUNAMPE – SIMON','917289473','21861580','F1'),
A99: 113 | B99: HERRERA VILLA JORGE LUIS | C99: PSJ. PRIMAVERA 100 LT 21 - CRUZ BLANCA | D99: CHINCHA ALTA | E99: ZONA: CRUZ BLANCA CAMPO | F99: 971343321 | G99: 21862344 | H99: F1 | I99: ="('"&B99&"','"&C99&"','"&D99&"','"&E99&"','"&F99&"','"&G99&"','"&H99&"')," -> ('HERRERA VILLA JORGE LUIS','PSJ. PRIMAVERA 100 LT 21 - CRUZ BLANCA','CHINCHA ALTA','ZONA: CRUZ BLANCA CAMPO','971343321','21862344','F1'),
A100: 114 | B100: YATACO GARCIA DE GARCIA NELLY | C100: PSJ. SAN JUAN DE DIOS MZ.-10 LT. 04 - CRUZ BLANCA - CHINCHA | D100: CHINCHA ALTA | E100: ZONA: CRUZ BLANCA PARTE ALTA oruro | F100: 912707222 | G100: 21862542 | H100: F1 | I100: ="('"&B100&"','"&C100&"','"&D100&"','"&E100&"','"&F100&"','"&G100&"','"&H100&"')," -> ('YATACO GARCIA DE GARCIA NELLY','PSJ. SAN JUAN DE DIOS MZ.-10 LT. 04 - CRUZ BLANCA - CHINCHA','CHINCHA ALTA','ZONA: CRUZ BLANCA PARTE ALTA oruro','912707222','21862542','F1'),
...

Sheet análisis
B6: DISTRITOS | C6: TOTAL
B7: CHINCHA ALTA | C7: 221
B8: GROCIO PRADO | C8: 43
B9: PUEBLO NUEVO | C9: 81
B10: SUNAMPE | C10: 358
B11: TAMBO DE MORA | C11: 16
B12: Total general | C12: 719
E18: 30
B20: DISTRITOS | C20: TOTAL | D20: % | E20: CANASTAS % | F20: CANASTAS
B21: CHINCHA ALTA | C21: 221 | D21: =(C21/$C$26)*100 -> 30.737135 | E21: =(D21*$E$18)/100 -> 9.2211405 | F21: 9
B22: GROCIO PRADO | C22: 43 | D22: =(C22/$C$26)*100 -> 5.9805285 | E22: =(D22*$E$18)/100 -> 1.7941586 | F22: 2
B23: PUEBLO NUEVO | C23: 81 | D23: =(C23/$C$26)*100 -> 11.265647 | E23: =(D23*$E$18)/100 -> 3.379694 | F23: 3
B24: SUNAMPE | C24: 358 | D24: =(C24/$C$26)*100 -> 49.791377 | E24: =(D24*$E$18)/100 -> 14.937413 | F24: 14
B25: TAMBO DE MORA | C25: 16 | D25: =(C25/$C$26)*100 -> 2.2253129 | E25: =(D25*$E$18)/100 -> 0.66759388 | F25: 2
C26: =SUM(C21:C25) -> 719 | D26: =SUM(D21:D25) -> 100 | E26: =SUM(E21:E25) -> 30 | F26: =SUM(F21:F25) -> 30
E28: 30 | F28: 100
E29: ? | F29: 30
